Workbook
Name BULAN: [1]KASUS10!$I$23:$I$202
Name JKL: [2]parameter!$E$163:$E$164
Name JKW: [2]parameter!$E$190:$E$211
Name kolek: '[3]ASPEK KEU'!$K$46:$K$50
Name PENY: [2]parameter_tier!$E$141:$E$161
Name PKR: [2]parameter!$E$174:$E$177
Name PKS: [2]parameter!$E$184:$E$187
Name S1A: [2]parameter!$E$6:$E$9
Name S1B: [2]parameter!$E$11:$E$12
Name S1C: [2]parameter!$E$14:$E$17
Name S1D: [2]parameter!$E$19:$E$22
Name S2A: [2]parameter!$E$26:$E$29
Name S2B: [2]parameter!$E$31:$E$34
Name S2C: [2]parameter!$E$36:$E$39
Name S3A: [2]parameter!$E$43:$E$46
Name S3B: [2]parameter_tier!$E$48:$E$55
Name S3C: [2]parameter!$E$53:$E$55
Name S3D: [2]parameter!$E$57:$E$60
Name S3E: [2]parameter!$E$62:$E$65
Name S3F: [2]parameter!$E$67:$E$70
Name S3I: [2]parameter!$E$86:$E$89
Name S3J: [2]parameter!$E$91:$E$94
Name S3K: [2]parameter!$E$96:$E$99
Name S4A: [2]parameter!$E$103:$E$106
Name S4D: [2]parameter!$E$118:$E$121
Name S6A: [2]parameter!$E$132:$E$133
Name STA: [2]parameter!$E$180:$E$181
Name TUJ: [2]parameter!$E$159:$E$160

Sheet Informasi Pokok
A2: Kantor (PG) | C2: :
A3: Nomor REGISTER | C3: :
A4: Nomor PROPOSAL | C4: :
A5: Nama AO (M) | C5: : | M5: =" /BPRS-AU/"&M8&"/"&L6 -> /BPRS-AU/V/2025
A6: Tanggal Analisa (M) | C6: : | L6: =YEAR(D6)
A8: 1. INFORMASI POKOK | L8: =MONTH(D6) | M8: =VLOOKUP(L8,L11:M24,2,0)
A10: 1 | B10: Jenis Kategori Nasabah (PG) | F10: =IF(D10="Referral","Nama :","")
A11: =A10+1 | B11: Nama (M) | C11: : | L11: 1 | M11: I
A12: 3 | B12: Jenis Kelamin | C12: :
A13: 4 | B13: Tempat Lahir (M) | C13: : | G13: Tanggal Lahir : | L13: 2 | M13: II
A14: =A13+1 | B14: NIK (M) | C14: : | G14: Usia : | I14: =IF(Parameter!G32<=2,Parameter!E253,Parameter!E254) | L14: 3 | M14: III | N14: 21 - 30 tahun | O14: 21 - 30 tahun
A15: =A14+1 | B15: Alamat (M) | C15: : | L15: 4 | M15: IV | N15: 31 - 40 tahun | O15: 31 - 40 tahun
L16: 5 | M16: V | N16: 41 - 50 tahun | O16: 41 - 50 tahun
D17: Desa/Kelurahan : | H17: Kecamatan : | L17: 6 | M17: VI | N17: 51 - 55 tahun | O17: 51 - 60 tahun
D18: Kab./Kotamadya : | H18: Kode Pos : | L18: 7 | M18: VII
A19: =A18+1 | B19: Telpon Rumah | C19: :
A20: =A15+1 | B20: HP (M) | C20: : | L20: 8 | M20: VIII
A21: =A20+1 | B21: Status Pernikahan (PG) | C21: : | L21: 9 | M21: IX
A22: =A21+1 | B22: Jumlah Tanggungan (PG) | C22: : | L22: 10 | M22: X
A23: =A22+1 | B23: Pendidikan Terakhir (PG) | C23: : | L23: 11 | M23: XI
A24: =A23+1 | B24: Kepemilikan Tempat Tinggal (PG) | C24: : | L24: 12 | M24: XII
A25: =A24+1 | B25: Status Karyawan (PG) | C25: :
A26: =A25+1 | B26: Bidang Usaha Pekerjaan (PG) | C26: :
A27: =A26+1 | B27: Bonafiditas Perusahaan (PG) | C27: :
A28: =A27+1 | B28: Usia Pensiun (O) | C28: : | D28: =IF(Parameter!G32<=2,Parameter!H253,Parameter!H254) | E28: Tahun
A29: =A28+1 | B29: Surat Keterangan Bekerja (PG) | C29: :
A30: =A29+1 | B30: Slip Gaji (PG) | C30: :
A31: =A30+1 | B31: Rekening Gaji (PG) | C31: :
A32: =A31+1 | B32: MoU dengan BPRS Amanah Ummah
A33: =A32+1 | B33: Surat Kuasa Potong Gaji
A34: =A33+1 | B34: Reputasi di Tempat Kerja dan Tempat Tinggal (PG) | C34: :
A35: =A34+1 | B35: Indikator Reputasi di Tempat Kerja dan Tempat Tinggal (M) | C35: :
A36: =A35+1 | B36: Nama Gadis Ibu Kandung (M) | C36: : | L36: Sistem Penj | M36: Konsinyasi / Bagi Hasil
A37: =A36+1 | B37: Nama Pasangan (Suami-Istri) (M) | C37: :
A38: =A37+1 | B38: Tempat/Tanggal Lahir (M) | C38: :
A39: =A38+1 | B39: No. KTP/SIM/Paspor (M) | C39: :
A40: =A39+1 | B40: Pekerjaan Pasangan (Suami-Istri) (M) | C40: :
A41: =A40+1 | B41: Nama Anak Yang Dapat | C41: : | M41: Kredit & Tunai
B42: Dihubungi dan Tidak Serumah (M) | M42: Kredit
A43: =A41+1 | B43: HP (M) | C43: : | M43: Lain-lain
M45: 12
A46: 2. HUBUNGAN DENGAN PERBANKAN | M46: 13
M47: 14
A48: 1 | B48: =Parameter!B81 | C48: : | M48: 15
A49: 2 | B49: =Parameter!B86 | C49: : | M49: 18
M50: 19
A51: 3. PERMOHONAN PEMBIAYAAN | M51: 24
M52: 36
A53: 1 | B53: Permohonan Pembiayaan Ke- (M) | C53: : | E53: =IF(D53="",0,Parameter!T114) | M53: 48
A54: 2 | B54: Bukti Penggunaan Dana Pembiayaan Sebelumnya (PG) | C54: :
A55: 3 | B55: Jumlah Permohonan (M) | C55: : | M55: 48
A56: 4 | B56: Jangka Waktu/Bulan (PG) | C56: : | E56: Bulan | M56: 50
A57: 5 | B57: ="Penawaran Setara "&'[4]Usulan Pembiayaan'!AD20&"/Bulan" | C57: :
A58: 6 | B58: Akad Pembiayaan (PG) | C58: : | M58: 52
A59: 7 | B59: Sektor Ekonomi (PG) | C59: :
A60: 8 | B60: Jenis Penggunaan (PG) | C60: :
A61: 9 | B61: Tujuan Penggunaan Dana (M) | C61: :
A62: 10 | B62: Tanggal Permohonan (M) | C62: :
H63: Pengusul,
H66: =D5
H67: Account Officer
B69: Perhatian:
B70: M: Manual
B71: O: Otomatis
B72: PG: Pilihan Ganda
B73: Kotak Warna Putih Diisi Manual
B74: Kotak Warna Kuning Jangan Diisi Manual (Otomatis)
M349: Murabahah
M350: Istishna
M351: Salam
M352: Ijarah
M353: IMBT
M354: Ijarah Multijasa
M355: Musyarakah
M356: MMQ
M357: Mudharabah
M358: Qardh
M359: Qardh Haji
M399: 1 Modal Kerja
... M401: 3 Konsumtif

Sheet Aspek Non Keuangan
A1: ASPEK NON KEUANGAN
A3: ASPEK MANAJEMEN
A4: a. | B4: Latar Belakang Nasabah (M)
A5: -
A6: -
A10: -
A13: -
A16: b. | B16: Pengalaman Bekerja Nasabah (M) | J16: :
A19: c. | B19: Alamat Perusahaan (M) | J19: :
G23: ASPEK LEGALITAS NASABAH
G24: Nama Instansi/Lembaga | M24: :
G25: Nomor SK | M25: :
G26: Tanggal | M26: :
G27: Atas Nama | M27: :
A29: ASPEK LEGALITAS AGUNAN
A31: - Agunan Tanah/Bangunan
A32: No | B32: Jenis Surat/Dokumen (PG) | G32: No. | H32: Atas Nama (M) | L32: LT2 | M32: LB2 | N32: Nilai Pasar | P32: Nilai | Q32: Os. Pokok | R32: Nilai Bank (O) | V32: Peng ikatan (PG) | X32: Lokasi Agunan (M)
N33: KJPP/Internal (M) | P33: Agunan (%) (M) | Q33: Paripasu (M)
A34: 1 | R34: =(N34*P34)-Q34
A36: =A35+1 | R36: =(N36*P36)-Q36
A37: =A36+1 | R37: =(N37*P37)-Q37
A38: =A37+1 | R38: =(N38*P38)-Q38
A39: =A38+1 | R39: =(N39*P39)-Q39
A40: =A39+1 | R40: =(N40*P40)-Q40
A41: Total (O) | N41: =SUM(N34:O40) | R41: =SUM(R34:U40)
A43: - Agunan Kendaraan Bermotor
A44: No | B44: BPKB-Merek | E44: Type | H44: Thn | I44: Atas Nama | L44: No. BPKB | N44: Nopol | O44: Nilai Pasar | Q44: Nilai Agunan | R44: Os. Pokok | V44: Nilai Bank (O) | Z44: Pengikatan (PG)
O45: KJPP/Internal (M) | Q45: (%) (M) | R45: Paripasu (M)
A47: 2 | Q47: 0.8 | V47: =(O47*Q47)-R47
A48: 3 | Q48: 0.8 | V48: =(O48*Q48)-R48
A49: 4 | Q49: 0.8 | V49: =(O49*Q49)-R49
A50: 5 | Q50: 0.8 | V50: =(O50*Q50)-R50
A51: Total (O) | O51: =SUM(O46:P50) | R51: =SUM(R46:U50) | V51: =SUM(V46:Y50)
A53: - Surat Berharga/Logam Mulia
A54: No | B54: Jenis | E54: Nomor | H54: Atas Nama | L54: Nominal (M) | O54: Nilai Agunan (%) (M) | Q54: Os. Pokok | S54: Nilai Bank (O)
Q55: Paripasu (M)
A56: 1 | O56: 1 | S56: =(L56*O56)-Q56
A57: 2 | O57: 1 | S57: =(L57*O57)-Q57
A58: 3 | O58: 1 | S58: =(L58*O58)-Q58
A59: 4 | O59: 1 | S59: =(L59*O59)-Q59
A60: Total (O) | L60: =SUM(L56:N59) | Q60: =SUM(Q56:R59) | S60: =SUM(S56:W59)
B62: Total Nilai Agunan (O) : | I62: =R41+V51+S60
A64: MANAJEMEN RISIKO
A66: 1. | B66: Risiko Kerja | AB66: - Usaha (Pengusaha): Moral Hazar, Omset Usaha Menurun dll
B67: - Pegawai/Karyawan: PHK, Moral Hazar, Perusahaan Bangkrut
B68: Mitigasi Risiko | E68: : | F68: Pick-Up Angsuran/Adanya Agunan
A70: 2. | B70: Risiko Pembayaran Angsuran | AB70: - Lembaga Pendidikan: Moral Hazar Pengurus, Konflik Pengurus, Jumlah Siswa/Santri/Mahasiswa Menurun
B71: Risiko: Tunggakan pembayaran angsuran pembiayaan
B72: Mitigasi Risiko | E72: : | F72: Remedial (Surat Panggilan/Surat Peringatan/Somasi)/Eksekusi Agunan
B73: Catatan : | C73: Kartu ATM dan Buku tabungan sebagai alat trasaksi gaji
C74: Disimpan dikantor sampai dengan pembiayaan lunas
A75: 3. | B75: Risiko Hukum
B76: Nasabah Wanprestasi/Melakukan Gugatan Hukum/Penyalahgunaan Agunan.
B77: Mitigasi Risiko | E77: :
B78: Mitigasi Risiko | E78: : | F78: Non Litigasi (Musyawarah/Mediasi)
B79: Mitigasi Risiko | E79: : | F79: Litigasi, Gugatan Melalui (PA/KPKNL/Kepolisian)
A81: 4. | B81: Risiko Kematian
B82: - Nasabah meninggal dunia
B83: Mitigasi Risiko | E83: :
A85: 5. | B85: Risiko Agunan
B86: - Agunan rumah/bangunan kebakaran
B87: - Agunan kendaraan hilang/rusak
B88: Mitigasi Risiko | E88: :
A90: VERIFIKASI
L92: Mengetahui | R92: Pengusul,
R96: ='Informasi Pokok'!D5
L97: Koord Marketing | R97: Account Officer
B99: PETUGAS VERIFIKASI | O99: CATATAN
C100: Nama | G100: :
C101: Jabatan | G101: : | H101: Manajer Bisnis
C102: Tanggal | G102: :
C103: Tanda tangan | G103: :
B107: PETUGAS VERIFIKASI | O107: CATATAN
C108: Nama | G108: :
C109: Jabatan | G109: : | H109: Kepala Cabang
C110: Tanggal | G110: :
C111: Tanda tangan | G111: :
AC307: Sertipikat Hak Milik
AC308: Sertipikat Hak Guna Bangunan
AC309: Sertipikat Rusun/Apartemen
AC310: Sertipikat Hak Guna Usaha
AC311: Akta Jual Beli
AC312: Akta Hibah
AC313: SIPTB
AC320: APHT
AC321: SKMHT&APHT
AC322: SKMHT
AC323: Legalisasi
AC324: Warmeking
... AC330: Di Bawah Tangan

Sheet Aspek Keuangan
A1: ANALISA KEUANGAN
A3: 1. PENDAPATAN TETAP
C5: Gaji Bulanan (THP) (M) | L5: :
C6: Uang Lembur (M) | L6: :
C7: Pendapatan Tetap Lainnya (M) | L7: :
C8: Total Pendapatan Tetap (O) | L8: : | M8: =SUM(M5:O7)
C10: Persentase Potongan Gaji (%)(PG) | L10: : | AE10: 0.3
C12: RPC/NPM | L12: : | M12: =M8*M10
A14: 2. PENDAPATAN TIDAK TETAP
B16: PENJUALAN
B18: No | C18: Nama Barang | H18: BULAN I | O18: BULAN II | W18: BULAN III
H19: Hari | I19: Omset/Hari | L19: Omset/Bulan | O19: Hari | P19: Omset/Hari | S19: Omzet/Bulan | W19: Hari | X19: Omset/Hari | Z19: Omset/Bulan (O)
B20: 1 | L20: =H20*I20 | S20: =O20*P20 | Z20: =X20*W20
B21: 2 | L21: =H21*I21 | S21: =O21*P21 | Z21: =X21*W21
B22: Total | I22: =SUM(I20:K21) | L22: =SUM(L20:N21) | P22: =SUM(P20:R21) | S22: =SUM(S20:U21) | X22: =SUM(X20:Y21) | Z22: =SUM(Z20:AB21)
B26: No | C26: Nama Barang | H26: RATA-RATA | O26: HPP
H27: Hari | I27: Omzet/Hari | L27: Omzet/Bulan | O27: % | P27: Nominal
B28: 1 | C28: =C20 | H28: =(H20+O20+W20)/3 | I28: =(I20+P20+X20)/3 | L28: =(L20+S20+Z20)/3 | P28: =L28*O28
B29: 2 | C29: =C21 | H29: =(H21+O21+W21)/3 | I29: =(I21+P21+X21)/3 | L29: =(L21+S21+Z21)/3 | P29: =L29*O29
B30: Total | H30: =AVERAGE(H28:H29) | I30: =SUM(I28:K29) | L30: =SUM(L28:N29) | O30: =AVERAGE(O28:O29) | P30: =SUM(P28:S29)
B32: Rata-Rata Penjualan 3 Bulan Terakhir | M32: : | N32: =(L22+S22+Z22)/3
A34: 3. BIAYA TENAGA KERJA
C36: Jumlah Tenaga Kerja Yang Digaji Harian (M) | L36: :
C37: Besarnya Upah Per Hari Per Orang (M) | L37: :
C39: Jumlah Tenaga Kerja Yang Digaji Mingguan (M) | L39: :
C40: Besarnya Upah Per Minggu Per Orang (M) | L40: :
C42: Jumlah Tenaga Kerja Yang Digaji Bulanan (M) | L42: :
C43: Besarnya Upah Per Bulan Per Orang (M) | L43: : | AN43: : | AO43: 0.2
C45: TOTAL BIAYA TENAGA KERJA (O) | L45: : | M45: =(M36*M37*30)+(M39*M40*4)+(M42*M43)
A47: 4. BIAYA USAHA
C49: Biaya LISTRIK & Air Tempat Usaha (M) | L49: :
C50: Biaya Perawatan (M) | L50: :
C51: Biaya SEWA Tempat Usaha (M) | L51: :
C52: Biaya Transportasi & Perawatan (M) | L52: :
C53: Biaya HANDPHONE Usaha (M) | L53: :
C55: TOTAL BIAYA USAHA (O) | L55: : | M55: =SUM(M49:O54)
A57: 4. LABA RUGI USAHA
C59: Penjualan | L59: : | M59: =N32 | AE59: 0.3
C60: HPP | L60: : | M60: =P30 | AE60: 0.35
C61: Laba Kotor | L61: : | M61: =M59-M60
C62: Total Biaya | L62: : | M62: =M45+M55 | AE62: 0.4
C63: Laba Sebelum Pajak | L63: : | M63: =(M59-M60)-M62 | AE63: 0.7
C64: Taksiran Pajak | M64: =M63*5%
C65: Laba Bersih | L65: : | M65: =M63-M64 | AE65: 0.7
C67: % RPC/NPM | L67: : | AE67: 0.8
C69: Repayment Capacity | L69: : | M69: =M65*M67
A71: 3. HUBUNGAN BANK
A72: Calon Nasabah
A73: No | B73: Nama Bank | F73: Plafond | I73: Os. Pokok | L73: Margin/ Tahun | N73: Angsuran/ Bulan | Q73: Tgl. Mulai | T73: Tgl. Akhir | W73: Pangsa | Y73: % | Z73: Kol | AA73: Dilunasi
A74: 1 | I74: =IF(Y74="Flat",AP74,AO74) | N74: =IF(AA74="Ya",0,AE74) | Y74: Efektif | AA74: Ya | AE74: =IF(Y74="Flat",AI74,AK74) | AF74: =IF(AA74="Ya",I74,0) | AG74: =IF(AA74="Ya",B74,"") | AH74: =DATEDIF(Q74,T74,"M") | AI74: =IFERROR(F74/Parameter!D256,"0")+IFERROR(F74*(L74/12),"") | AJ74: =PMT(L74/12,AH74,-F74) | AK74: =IFERROR(AJ74,0) | AL74: =Parameter!F256 | AM74: =(AH74/12)*L74 | AN74: =F74*(1+AM74/AH74)^AL74-(AK74*((1+AM74/AH74)^AL74-1)/(AM74/AH74)) | AO74: =IFERROR(AN74,0) | AP74: =IFERROR(Parameter!G256*Parameter!G257,"")
A75: 2 | I75: =IF(Y75="Flat",AP75,AO75) | N75: =IF(AA75="Ya",0,AE75) | Y75: Efektif | AA75: Ya | AE75: =IF(Y75="Flat",AI75,AK75) | AF75: =IF(AA75="Ya",I75,0) | AG75: =IF(AA75="Ya",B75,"") | AH75: =DATEDIF(Q75,T75,"M") | AI75: =IFERROR(F75/Parameter!D258,"0")+IFERROR(F75*(L75/12),"") | AJ75: =PMT(L75/12,AH75,-F75) | AK75: =IFERROR(AJ75,0) | AL75: =Parameter!F258 | AM75: =(AH75/12)*L75 | AN75: =F75*(1+AM75/AH75)^AL75-(AK75*((1+AM75/AH75)^AL75-1)/(AM75/AH75)) | AO75: =IFERROR(AN75,0) | AP75: =IFERROR(Parameter!G258*Parameter!G259,"")
A77: 4 | I77: =IF(Y77="Flat",AP77,AO77) | N77: =IF(AA77="Ya",0,AE77)
A78: 5 | I78: =IF(Y78="Flat",AP78,AO78) | N78: =IF(AA78="Ya",0,AE78)
A79: 6 | I79: =IF(Y79="Flat",AP79,AO79) | N79: =IF(AA79="Ya",0,AE79) | AE79: =IF(Y79="Flat",AI79,AK79) | AF79: =IF(AA79="Ya",I79,0) | AG79: =IF(AA79="Ya",B79,"") | AH79: =DATEDIF(Q79,T79,"M") | AI79: =IFERROR(F79/Parameter!D262,"0")+IFERROR(F79*(L79/12),"") | AJ79: =PMT(L79/12,AH79,-F79) | AK79: =IFERROR(AJ79,0) | AL79: =Parameter!F262 | AM79: =(AH79/12)*L79 | AN79: =F79*(1+AM79/AH79)^AL79-(AK79*((1+AM79/AH79)^AL79-1)/(AM79/AH79)) | AO79: =IFERROR(AN79,0) | AP79: =IFERROR(Parameter!G262*Parameter!G263,"")
A80: 7 | I80: =IF(Y80="Flat",AP80,AO80) | N80: =IF(AA80="Ya",0,AE80) | AE80: =IF(Y80="Flat",AI80,AK80) | AF80: =IF(AA80="Ya",I80,0) | AG80: =IF(AA80="Ya",B80,"") | AH80: =DATEDIF(Q80,T80,"M") | AI80: =IFERROR(F80/Parameter!D264,"0")+IFERROR(F80*(L80/12),"") | AJ80: =PMT(L80/12,AH80,-F80) | AK80: =IFERROR(AJ80,0) | AL80: =Parameter!F264 | AM80: =(AH80/12)*L80 | AN80: =F80*(1+AM80/AH80)^AL80-(AK80*((1+AM80/AH80)^AL80-1)/(AM80/AH80)) | AO80: =IFERROR(AN80,0) | AP80: =IFERROR(Parameter!G264*Parameter!G265,"")
A81: TOTAL (O) | F81: =SUM(F74:H80) | I81: =SUM(I74:K80) | N81: =SUM(N74:P80) | AD81: total | AE81: =SUM(AE74:AE80) | AF81: =SUM(AF74:AF80)
A83: Keterangan :
A86: Pasangan
A87: No | B87: Nama Bank | F87: Plafond | I87: Os. Pokok | L87: Margin/ Tahun | N87: Angsuran/ Bulan | Q87: Tgl. Mulai | T87: Tgl. Akhir | W87: Pangsa | Y87: % | Z87: Kol | AA87: Dilunasi
A90: 3 | I90: =IF(Y90="Flat",AP90,AO90) | N90: =IF(AA90="Ya",0,AE90) | AE90: =IF(Y90="Flat",AI90,AK90) | AF90: =IF(AA90="Ya",I90,0) | AG90: =IF(AA90="Ya",B90,"") | AH90: =DATEDIF(Q90,T90,"M") | AI90: =IFERROR(F90/Parameter!D271,"0")+IFERROR(F90*(L90/12),"") | AJ90: =PMT(L90/12,AH90,-F90) | AK90: =IFERROR(AJ90,0) | AL90: =Parameter!F271 | AM90: =(AH90/12)*L90 | AN90: =F90*(1+AM90/AH90)^AL90-(AK90*((1+AM90/AH90)^AL90-1)/(AM90/AH90)) | AO90: =IFERROR(AN90,0) | AP90: =IFERROR(Parameter!G271*Parameter!G272,"")
A91: 4 | I91: =IF(Y91="Flat",AP91,AO91) | N91: =IF(AA91="Ya",0,AE91) | AE91: =IF(Y91="Flat",AI91,AK91) | AF91: =IF(AA91="Ya",I91,0) | AG91: =IF(AA91="Ya",B91,"") | AH91: =DATEDIF(Q91,T91,"M") | AI91: =IFERROR(F91/Parameter!D273,"0")+IFERROR(F91*(L91/12),"") | AJ91: =PMT(L91/12,AH91,-F91) | AK91: =IFERROR(AJ91,0) | AL91: =Parameter!F273 | AM91: =(AH91/12)*L91 | AN91: =F91*(1+AM91/AH91)^AL91-(AK91*((1+AM91/AH91)^AL91-1)/(AM91/AH91)) | AO91: =IFERROR(AN91,0) | AP91: =IFERROR(Parameter!G273*Parameter!G274,"")
A92: 5 | I92: =IF(Y92="Flat",AP92,AO92) | N92: =IF(AA92="Ya",0,AE92) | AE92: =IF(Y92="Flat",AI92,AK92) | AF92: =IF(AA92="Ya",I92,0) | AG92: =IF(AA92="Ya",B92,"") | AH92: =DATEDIF(Q92,T92,"M") | AI92: =IFERROR(F92/Parameter!D275,"0")+IFERROR(F92*(L92/12),"") | AJ92: =PMT(L92/12,AH92,-F92) | AK92: =IFERROR(AJ92,0) | AL92: =Parameter!F275 | AM92: =(AH92/12)*L92 | AN92: =F92*(1+AM92/AH92)^AL92-(AK92*((1+AM92/AH92)^AL92-1)/(AM92/AH92)) | AO92: =IFERROR(AN92,0) | AP92: =IFERROR(Parameter!G275*Parameter!G276,"")
A93: TOTAL (O) | F93: =SUM(F88:H92) | I93: =SUM(I88:K92) | N93: =SUM(N88:P92) | AD93: total | AE93: =SUM(AE88:AE92) | AF93: =SUM(AF88:AF92)
A95: Keterangan : | E95: Data Pembiayaan/Kredit berdasarkan hasil Slik OJK (data Slik terlampir)
B98: PELUNASAN BANK
B99: Nama Bank | M99: Baki Debet | P99: Biaya Lain-Lain
B100: ="Debitur: "&AG74&"-"&AG75&"-"&AG76&"-"&AG79&"-"&AG80 | M100: =AF81
B101: ="Debitur: "&AG88&"-"&AG89&"-"&AG90&"-"&AG91&"-"&AG92 | M101: =AF93
B103: JUMLAH PELUNASAN (O) | M103: =M100+P100+M101+P101
A105: VERIFIKASI
M107: Mengetahui | T107: Pengusul,
T111: ='Informasi Pokok'!D5
M112: Koord Marketing | T112: Account Officer
B114: PETUGAS VERIFIKASI | O114: CATATAN
C115: Nama | G115: :
C116: Jabatan | G116: : | H116: Manajer Bisnis
C117: Tanggal | G117: :
C118: Tanda tangan | G118: :
B122: PETUGAS VERIFIKASI | O122: CATATAN
C123: Nama | G123: :
C124: Jabatan | G124: : | H124: Kepala Cabang
C125: Tanggal | G125: :
C126: Tanda tangan | G126: :

Sheet AKTIVITAS USAHA
A1: URAIAN AKTIVITAS USAHA DEBITUR/CALON DEBITUR
A3: ASPEK PEMASARAN
A4: A. | B4: TINGKAT PERMINTAAN
B5: Performance Indicator | H5: Uraian Singkat
B6: Ukuran target pasar (market size) | H6: Tingkat konsumsi tinggi, daya beli tinggi
B8: Luas area geografis target pasar. | H8: Regional
B10: Pola/sifat permintaan target pasar | H10: stabil
B12: Pertumbuhan permintaan target pasar | H12: Diperkirakan 0% s/d 5%
B14: Pangsa Pasar Perusahaan | H14: Diperkirakan 20 besar
B15: Diversifikasi segmen pasar perusahaan | H15: 5 segmen atau lebih
B17: Realisasi penjualan dibanding target | H17: Penjualan kurang dari 50% target
A20: B. | B20: KUALITAS PRODUK ATAU JASA
B21: Performance Indicator | H21: Uraian Singkat
B22: Kualitas produk/jasa | H22: ◊ | I22: Reliabilitas/Keandalan
H26: ◊ | I26: Jaminan Kepastian
H30: ◊ | I30: Pelayanan
I31: Produk yang ditawarkan cukup dikenal oleh masyarakat, dan tetap digunakan di setiap waktu.
H34: ◊ | I34: Empati
I35: Kebutuhan pelanggan terhadap produk tsb tetap dipertahankan. Apabila pelanggan mengeluh, pemohon mengantisipasi dengan cepat. Hal ini terlihat banyaknya pelanggan pemohon.
H38: ◊ | I38: Responsif
I39: Pemohon mampu memberikan pelayanan dan pengiriman yang cepat kepada pelanggannya. Hal ini terlihat dari jumlah alat transportasi yang digunakan oleh pemohon.
B43: Tingkat harga produk/jasa | H43: Di bawah harga pasar.
B45: Rentang jenis produk (diversifikasi produk)
B49: Kekuatan merk (brand image) | H49: Untuk produk yang ditawarkan oleh pemohon beberapa produk telah cukup dikenal oleh para pelanggannya. Hal ini terlihat dari jumlah penjualan setiap harinya.
B53: Inovasi produk/jasa
B57: Jaringan distribusi | H57: Di atas 15 cabang/ outlet/agen/sales forces
B59: Syarat-syarat penjualan | H59: Syarat-syarat penjualan yang dilakukan pemohon antara lain:
I63: - | J63: Pemohon lebih mengutamakan pembayaran tunai
I64: - | J64: Untuk pembayaran kredit diperbolehkan dengan masa 1-2 hari
I65: - | J65: Penjualan ditargetkan sebanyak +/-50%
I66: -
A68: C. | B68: KONSENTRASI PELANGGAN
B69: Performance Indicator | H69: Uraian Singkat
B70: Proporsi penjualan per pelanggan | H70: 4 pelanggan menguasai 15% penjualan atau lebih
B72: Kualitas hubungan dengan pelanggan | H72: Hubungan antara pemohon dengan para pelanggannya telah terjalin baik hal ini terlihat antara lain:
I75: - | J75: Lamanya hubungan dengan pelanggan
I76: - | J76: Track record penyelesaian hak-kewajiban pelanggan
I77: - | J77: Untuk di wilayah tsb pemohon telah dikenal baik oleh para pelanggannya
B79: Daya tawar pelanggan | H79: Tawar menawar antara pelanggan dengan pemohon cukup baik. Hal ini terlihat dari beberapa faktor antara lain:
I82: - | J82: Planggan mengutamakan harga yang murah, hingga pelanggan
I83: -
I84: -
I85: -
I86: -
A88: D. | B88: TINGKAT PERSAINGAN
B89: Performance Indicator | H89: Uraian Singkat
B90: Kondisi persaingan | H90: +/- 20%
B92: Daya saing produk substitusi | H92: Daya saing produk pengganti dari produk pemohon antara lain:
I95: - | J95: Kecenderungan harga
I96: - | J96: Kualitas nya sangat bagus
I97: -
B98: Kekuatan penghalang masuk/keluar | H98: Penghalang masuk rendah & penghalang keluar tinggi
B103: Strategi persaingan | H103: Strategi persaingan usaha pemohon antara lain:
I106: - | J106: Kejelasan strategi yang digunakan
I107: - | J107: Kesesuaian strategi dengan kondisi (kekuatan-kelemahan) internal perusahaan.
I109: - | J109: Kesesuaian strategi dengan kondisi (peluang-ancaman) eksternal perusahaan.
I111: -
B113: Tingkat integrasi | H113: Mempunyai lebih dari satu aktivitas usaha yang tidak berkaitan.
B115: Hak patent atau lisensi | H115: Untuk usaha yang dijalankan, pemohon telah memiliki izin-izin dari pemerintahan setempat. Antara lain SIUP dan TDP.
A121: ASPEK TEKNIS/PRODUKSI
A123: E. | B123: KONDISI LOKASI USAHA
B124: Performance Indicator | H124: Uraian Singkat
B125: Kondisi lokasi usaha | H125: Kondisi lokasi usaha pemohon cukup baik, hal ini terlihat dari beberapa faktor, antara lain:
I127: - | J127: Sekitar lokasi usaha tidak terdapat usaha yang sejenis.
I128: - | J128: Lokasi usaha cukup dekat dengan para pelanggannya. Hal ini
I129: - | J129: yang cukup memudahkan pemohon untuk menjalankan usaha.
I130: -
B131: Kelayakan lahan usaha
B134: Ijin lokasi usaha | H134: Pemohon telah memiliki perijinan dari pemerintahan setempat.
I137: - | J137: Ketaatan perijinan lokasi usaha.
I138: - | J138: Ketaatan pengelolaan lingkungan
B139: Status kepemilikan lokasi usaha | H139: Hak pakai / guna usaha
A142: F. | B142: KONDISI PERALATAN
B143: Performance Indicator | H143: Uraian Singkat
B144: Kapasitas terpasang (size) dibanding dengan pesaing terdekat | H144: Jauh di atas rata-rata
B147: Kapasitas terpakai (utilitas) | H147: 61-80%
B149: Teknologi yang digunakan | H149: Modern
B151: Bio-teknologi
B155: Kondisi peralatan | H155: Kondisi sangat baik dan sangat terawat
B157: Dukungan vendor/supplier peralatan
I159: - | J159: Pelayanan purna jual
I160: - | J160: Tingkat kooperatif}
A162: G. | B162: PENILAIAN SUPPLY
B163: Performance Indicator | H163: Uraian Singkat
B164: Tingkat konsentrasi supplier | H164: 1 supplier menguasai 50 % pembelian atau lebih
B166: Kualitas hubungan dengan supplier | H166: Hubungan pemohon dengan supplier telah terjalin lama dan baik. Hal ini terlihat dari beberapa faktor antara lain
I169: - | J169: Lamanya hubungan dengan supplier
I170: - | J170: Track record penyelesaian hak-kewajiban pelanggan
I171: -
B175: Daya tawar supplier | H175: Daya tawar dari supplier terlihat dari beberapa faktor antara lain:
I177: - | J177: Persediaan barang terpenuhi dan tetap jalan.
I178: - | J178: Produk supplier merupakan bahan input yang penting bagi perusahaan.
I180: - | J180: Supplier telah banyak menjalin kerjasama dengan para pihak
I181: - | J181: penyediaan barang. Sehingga persediaan barang di tempat
I182: - | J182: tidak pernah habis
I183: -
B184: Kandungan bahan baku import | H184: Impor lebih dari 70%
B186: Ketersediaan bahan baku
I188: - | J188: Kuantitas bahan baku
I189: - | J189: Kualitas bahan baku
...

Sheet Rekening Koran & Aset
A1: BANK (M): | D1: Currency (M): | E1: IDR | G1: ='Informasi Pokok'!D6
A2: Nomor Rekening (M): | D2: Saldo Awal (M):
A3: Atas Nama (M): | C3: ='Informasi Pokok'!D11
A5: Bulan | B5: Mutasi Debet | C5: Mutasi Kredit | D5: Saldo | E5: Bulan | F5: Mutasi Debet | G5: Mutasi Kredit | H5: Saldo | I5: Bulan | J5: Mutasi Debet | K5: Mutasi Kredit | L5: Saldo
D6: =E2 | E6: =IF(A6="","",DATE(YEAR(A6),MONTH(A6)+1,DAY(A6))) | H6: =D53 | I6: =IF(E6="","",DATE(YEAR(E6),MONTH(E6)+1,DAY(E6))) | L6: =H53 | M6: Bulan | N6: FQ | O6: Debet | P6: Rata2 Transaksi | Q6: FQ | R6: Kredit | S6: Rata2 Transaksi | T6: Saldo Akhir
A7: =$A$6 | D7: =D6-B7+C7 | E7: =$E$6 | H7: =H6-F7+G7 | I7: =$I$6 | L7: =L6-J7+K7 | M7: =A6 | N7: =B57 | O7: =B55 | P7: =B56 | Q7: =C57 | R7: =C55 | S7: =C56 | T7: =D53
A8: =$A$6 | D8: =D7-B8+C8 | E8: =$E$6 | H8: =H7-F8+G8 | I8: =$I$6 | L8: =L7-J8+K8 | M8: =E6 | N8: =F57 | O8: =F55 | P8: =F56 | Q8: =G57 | R8: =G55 | S8: =G56 | T8: =H53
A9: =$A$6 | D9: =D8-B9+C9 | E9: =$E$6 | H9: =H8-F9+G9 | I9: =$I$6 | L9: =L8-J9+K9 | M9: =I6 | N9: =J57 | O9: =J55 | P9: =J56 | Q9: =K57 | R9: =K55 | S9: =K56 | T9: =L53
A10: =$A$6 | D10: =D9-B10+C10 | E10: =$E$6 | H10: =H9-F10+G10 | I10: =$I$6 | L10: =L9-J10+K10 | M10: Rata-rata | N10: =AVERAGE(N7:N9) | O10: =AVERAGE(O7:O9) | P10: =AVERAGE(P7:P9) | Q10: =AVERAGE(Q7:Q9) | R10: =AVERAGE(R7:R9) | S10: =AVERAGE(S7:S9) | T10: =AVERAGE(T7:T9)
A11: =$A$6 | D11: =D10-B11+C11 | E11: =$E$6 | H11: =H10-F11+G11 | I11: =$I$6 | L11: =L10-J11+K11
A12: =$A$6 | D12: =D11-B12+C12 | E12: =$E$6 | H12: =H11-F12+G12 | I12: =$I$6 | L12: =L11-J12+K12
A13: =$A$6 | D13: =D12-B13+C13 | E13: =$E$6 | H13: =H12-F13+G13 | I13: =$I$6 | L13: =L12-J13+K13
A14: =$A$6 | D14: =D13-B14+C14 | E14: =$E$6 | H14: =H13-F14+G14 | I14: =$I$6 | L14: =L13-J14+K14
A15: =$A$6 | D15: =D14-B15+C15 | E15: =$E$6 | H15: =H14-F15+G15 | I15: =$I$6 | L15: =L14-J15+K15
A16: =$A$6 | D16: =D15-B16+C16 | E16: =$E$6 | H16: =H15-F16+G16 | I16: =$I$6 | L16: =L15-J16+K16
A17: =$A$6 | D17: =D16-B17+C17 | E17: =$E$6 | H17: =H16-F17+G17 | I17: =$I$6 | L17: =L16-J17+K17
A18: =$A$6 | D18: =D17-B18+C18 | E18: =$E$6 | H18: =H17-F18+G18 | I18: =$I$6 | L18: =L17-J18+K18
A19: =$A$6 | D19: =D18-B19+C19 | E19: =$E$6 | H19: =H18-F19+G19 | I19: =$I$6 | L19: =L18-J19+K19
A20: =$A$6 | D20: =D19-B20+C20 | E20: =$E$6 | H20: =H19-F20+G20 | I20: =$I$6 | L20: =L19-J20+K20
A21: =$A$6 | D21: =D20-B21+C21 | E21: =$E$6 | H21: =H20-F21+G21 | I21: =$I$6 | L21: =L20-J21+K21
A22: =$A$6 | D22: =D21-B22+C22 | E22: =$E$6 | H22: =H21-F22+G22 | I22: =$I$6 | L22: =L21-J22+K22
... A53: =$A$6 | D53: =D52-B53+C53 | E53: =$E$6 | H53: =H52-F53+G53 | I53: =$I$6 | L53: =L52-J53+K53
A55: Total | B55: =SUM(B7:B53) | C55: =SUM(C7:C53) | E55: Total | F55: =SUM(F7:F53) | G55: =SUM(G7:G53) | I55: Total | J55: =SUM(J7:J53) | K55: =SUM(K7:K53)
A56: Average | B56: =AVERAGE(B7:B53) | C56: =AVERAGE(C7:C53) | E56: Average | F56: =AVERAGE(F7:F53) | G56: =AVERAGE(G7:G53) | I56: Average | J56: =AVERAGE(J7:J53) | K56: =AVERAGE(K7:K53)
A57: FQ | B57: =COUNT(B7:B53) | C57: =COUNT(C7:C53) | F57: =COUNT(F7:F53) | G57: =COUNT(G7:G53) | J57: =COUNT(J7:J53) | K57: =COUNT(K7:K53)
B60: ASSET YANG DIMILIKI
B62: Jenis Asset (M) | D62: Saldo Bank | F62: Jenis Asset (M)
B63: Jumlah (O) | D63: =T9 | F63: Jumlah (M)
B64: Nama Bank (O) | D64: =C1 | F64: Tahun Perolehan (M)
F65: Nilai Taksasi Bank (M)
B67: Jenis Asset (M) | F67: Jenis Asset (M)
B68: Jumlah (M) | F68: Jumlah (M)
B69: Tahun Perolehan (M) | F69: Tahun Perolehan (M)
B70: Nilai Taksasi Bank (M) | F70: Nilai Taksasi Bank (M)
B72: Total Asset (O) | E72: : | F72: =D63+H65+D70+H70
A75: VERIFIKASI
F77: Mengetahui | J77: Pengusul,
J81: ='Informasi Pokok'!D5
F82: Koord Marketing | J82: Account Officer
A84: PETUGAS VERIFIKASI | G84: CATATAN
B85: Nama | C85: :
B86: Jabatan | C86: : | D86: Manajer Bisnis
B87: Tanggal | C87: :
B88: Tanda tangan | C88: :
A92: PETUGAS VERIFIKASI | G92: CATATAN
B93: Nama | C93: :
B94: Jabatan | C94: : | D94: Kepala Cabang
B95: Tanggal | C95: :
B96: Tanda tangan | C96: :

Sheet Usulan Pembiayaan
A2: MEMORANDUM USULAN PEMBIAYAAN | AA2: kdprd | AB2: prd
B3: Nomor MUP | F3: : | G3: =" "&'Informasi Pokok'!D3 -> 021/Reg/BS-AR/V/2025 | AA3: 10 | AB3: Murabahah | AC3: Harga Pokok | AD3: Margin | AE3: Harga Jual | AF3: Harga Pokok Barang | AG3: Urbun/Uang Muka I | AH3: Urbun/Uang Muka II | AI3: ---∞∞∞∞∞¶¶¶¶¶∞∞∞∞∞--- | AJ3: Pembiayaan Bank | AK3: Angsuran Margin/Bulan | AL3: Expected Return/Bulan | AM3: Angsuran Pokok/Bulan | AN3: Total Angsuran/Bulan | AO3: =$J$49-$J$50-$J$51 | AP3: Surplus/Minus Cashflow
B4: Tanggal Usulan | F4: : | G4: =TODAY() | AA4: 11 | AB4: PKE | AC4: Harga Pokok | AD4: Margin | AE4: Harga Jual | AF4: Harga Pokok Barang | AG4: Urbun/Uang Muka I | AH4: Urbun/Uang Muka II | AI4: ---∞∞∞∞∞¶¶¶¶¶∞∞∞∞∞--- | AJ4: Pembiayaan Bank | AK4: Angsuran Margin/Bulan | AL4: Expected Return/Bulan | AM4: Angsuran Pokok/Bulan | AN4: Total Angsuran/Bulan | AO4: =$J$49-$J$50-$J$51 | AP4: Surplus/Minus Cashflow
B5: Dari | F5: : | G5: Account Officer | AA5: 20 | AB5: Istishna | AC5: Harga Pokok | AD5: Margin | AE5: Harga Jual | AF5: Harga Pokok Barang | AG5: Urbun/Uang Muka I | AH5: Urbun/Uang Muka II | AI5: ---∞∞∞∞∞¶¶¶¶¶∞∞∞∞∞--- | AJ5: Pembiayaan Bank | AK5: Angsuran Margin/Bulan | AL5: Expected Return/Bulan | AM5: Angsuran Pokok/Bulan | AN5: Total Angsuran/Bulan | AO5: =$J$49-$J$50-$J$51 | AP5: Surplus/Minus Cashflow
B6: Kepada | F6: : | G6: Komite Pemutus Pembiayaan (KMPP) | AA6: 30 | AB6: Salam | AC6: Harga Pokok | AD6: Margin | AE6: Harga Jual | AF6: Harga Pokok Barang | AG6: Urbun/Uang Muka I | AH6: Urbun/Uang Muka II | AI6: ---∞∞∞∞∞¶¶¶¶¶∞∞∞∞∞--- | AJ6: Pembiayaan Bank | AK6: Angsuran Margin/Bulan | AL6: Expected Return/Bulan | AM6: Angsuran Pokok/Bulan | AN6: Total Angsuran/Bulan | AO6: =$J$49-$J$50-$J$51 | AP6: Surplus/Minus Cashflow
B7: Perihal | F7: : | G7: ="Permohonan Pembiayaan atas nama "&N14 | AA7: 50 | AB7: Ijarah | AC7: Harga Pokok Sewa | AD7: Ujroh | AE7: Harga Jual Sewa | AF7: Harga Pokok sewa | AG7: Urbun/Uang Muka I | AH7: Urbun/Uang Muka II | AI7: ---∞∞∞∞∞¶¶¶¶¶∞∞∞∞∞--- | AJ7: Pembiayaan Bank | AK7: Ujroh Sewa/Bulan | AL7: Ujroh Sewa (Setara)/Bulan | AM7: Angsuran Pokok Sewa/Bulan | AN7: Total Angsuran Sewa/Bln | AO7: =$J$49-$J$50-$J$51 | AP7: Surplus/Minus Cashflow
AA8: 51 | AB8: Ijarah Multijasa | AC8: Harga Pokok Sewa | AD8: Ujroh | AE8: Harga Jual Sewa | AF8: Harga Pokok sewa | AG8: Urbun/Uang Muka I | AH8: Urbun/Uang Muka II | AI8: ---∞∞∞∞∞¶¶¶¶¶∞∞∞∞∞--- | AJ8: Pembiayaan Bank | AK8: Ujroh Sewa/Bulan | AL8: Ujroh Sewa (Setara)/Bulan | AM8: Angsuran Pokok Sewa/Bulan | AN8: Total Angsuran Sewa/Bln | AO8: =$J$49-$J$50-$J$51 | AP8: Surplus/Minus Cashflow
B9: Assalamu'alaikum wr.wb. | AA9: 70 | AB9: Mudharabah | AC9: Pokok | AD9: Proyeksi Bagi Hasil | AE9: Total | AF9: Nilai Proyek | AG9: Modal Nasabah | AH9: Modal Bank | AI9: ---∞∞∞∞∞¶¶¶¶¶∞∞∞∞∞--- | AJ9: Pembiayaan Bank | AK9: Proyeksi Bagi Hasil/Bulan | AL9: Expected Return/Bulan | AM9: Proyeksi Angsuran Pokok/Bulan | AN9: Proyeksi Angsuran Pokok&Bagas/Bln | AO9: =$J$49-$J$50 | AP9: Proyeksi Surplus/Minus Cashflow
B10: ="Kami sampaikan Memorandum Usulan Pembiayaan atas nama "&N14&" dengan hal-hal sebagai berikut:" | AA10: 60 | AB10: Musyarakah | AC10: Pokok | AD10: Proyeksi Bagi Hasil | AE10: Total | AF10: Nilai Proyek | AG10: Modal Nasabah | AH10: Modal Bank | AI10: ---∞∞∞∞∞¶¶¶¶¶∞∞∞∞∞--- | AJ10: Pembiayaan Bank | AK10: Proyeksi Bagi Hasil/Bulan | AL10: Expected Return/Bulan | AM10: Proyeksi Angsuran Pokok/Bulan | AN10: Proyeksi Angsuran Pokok&Bagas/Bln | AO10: =$J$49-$J$50 | AP10: Proyeksi Surplus/Minus Cashflow
AA11: 65 | AB11: MMQ RS | AC11: Pokok (Hishah) | AD11: Bagi Hasil Atas Sewa | AE11: Harga Jual Sewa | AF11: Harga Pasar Aset | AG11: Harga Aset yang Dibeli Bank dari Nas. | AH11: Kepemilikan Aset Bank (Hishah) | AI11: Kepemilikan Aset Nasabah (Hishah) | AJ11: Harga Aset yang Disewa Nasabah | AK11: Ujroh Sewa/Bulan | AL11: Ujroh Sewa (Setara)/Bulan | AM11: Penebusan Aset/Hishah Oleh Nas. | AN11: Total Angsuran Sewa/Bln | AO11: =J49-J52 | AP11: Surplus/Minus Cashflow
A12: PERMOHONAN YANG DIAJUKAN | AA12: 52 | AB12: IMBT RS | AC12: Harga Pokok Sewa | AD12: Ujroh | AE12: Harga Jual Sewa | AF12: Harga Pasar Aset | AG12: Harga Aset yang Dibeli Bank dari Nas. | AH12: ---∞∞∞∞∞¶¶¶¶¶∞∞∞∞∞--- | AI12: ---∞∞∞∞∞¶¶¶¶¶∞∞∞∞∞--- | AJ12: Harga Aset yang Disewa Nasabah | AK12: Ujroh Sewa/Bulan | AL12: Ujroh Sewa (Setara)/Bulan | AM12: Angsuran Pokok Sewa/Bulan | AN12: Total Angsuran Sewa/Bln | AO12: =J50 | AP12: Surplus/Minus Cashflow
AA13: 40 | AB13: Qardh | AC13: Pokok | AD13: ---∞∞∞∞∞¶¶¶¶¶∞∞∞∞∞--- | AE13: ---∞∞∞∞∞¶¶¶¶¶∞∞∞∞∞--- | AF13: ---∞∞∞∞∞¶¶¶¶¶∞∞∞∞∞--- | AG13: ---∞∞∞∞∞¶¶¶¶¶∞∞∞∞∞--- | AH13: ---∞∞∞∞∞¶¶¶¶¶∞∞∞∞∞--- | AI13: ---∞∞∞∞∞¶¶¶¶¶∞∞∞∞∞--- | AJ13: Pembiayaan Bank | AK13: - | AL13: - | AM13: Angsuran Pokok | AN13: Total Angsuran/Bulan | AO13: =J49 | AP13: Surplus/Minus Cashflow
A14: 1 | B14: Nama Pemohon | L14: : | N14: ='Informasi Pokok'!D11
A15: 2 | B15: Akad Pembiayaan | L15: : | N15: ='Informasi Pokok'!D58
A16: 3 | B16: Jenis Penggunaan | L16: : | N16: ='Informasi Pokok'!D60
A17: 4 | B17: Jumlah Permohonan | L17: : | N17: ='Informasi Pokok'!D55
A18: 5 | B18: Expected Return/Bulan | L18: : | N18: ='Informasi Pokok'!D57 | R18: ='Informasi Pokok'!E57
A19: 6 | B19: Jangka Waktu | L19: : | N19: ='Informasi Pokok'!D56 | R19: Bulan | AB19: ='Informasi Pokok'!D58 | AC19: =VLOOKUP($AB$19,$AB$3:$AO$14,2,0) | AD19: =VLOOKUP($AB$19,$AB$3:$AO$14,3,0) | AE19: =VLOOKUP($AB$19,$AB$3:$AO$14,4,0) | AF19: =VLOOKUP($AB$19,$AB$3:$AO$14,5,0) | AG19: =VLOOKUP($AB$19,$AB$3:$AO$14,6,0) | AH19: =VLOOKUP($AB$19,$AB$3:$AO$14,7,0) | AI19: =VLOOKUP($AB$19,$AB$3:$AO$14,8,0) | AJ19: =VLOOKUP($AB$19,$AB$3:$AO$14,9,0) | AK19: =VLOOKUP($AB$19,$AB$3:$AO$14,10,0) | AL19: =VLOOKUP($AB$19,$AB$3:$AO$14,11,0) | AM19: =VLOOKUP($AB$19,$AB$3:$AO$14,12,0) | AN19: =VLOOKUP($AB$19,$AB$3:$AO$14,13,0) | AO19: =VLOOKUP($AB$19,$AB$3:$AO$14,14,0) | AP19: =VLOOKUP($AB$19,$AB$3:$AP$14,15,0)
A20: 7 | B20: Angsuran Perbulan | L20: : | N20: =IF(R18="Flat",AB20,AC20) | AB20: =(N17*N18*N19+N17)/N19 | AC20: =PMT(N18,N19,-N17)
A22: ANALISA KEUANGAN | AC22: 1.75 | AD22: 2
A24: 1 | B24: RPC Pendapatan Tetap | L24: : | N24: ='Aspek Keuangan'!M12
A25: 2 | B25: RPC Pendapatan Tidak Tetap | L25: : | N25: ='Aspek Keuangan'!M69
A26: 3 | B26: Kewajiban Kepada Pihak Lain | L26: : | N26: ='Aspek Keuangan'!N81+'Aspek Keuangan'!N93
A27: 4 | B27: Potensi Besarnya Angsuran | L27: : | N27: =(N24+N25)-N26
A29: ANALISA PLAFOND
A31: Plafond Maksimal | AA31: 1 | AB31: min | AC31: mid
I32: =AC19 | P32: : | Q32: =(Q34/(100%+(J54*J55))) | AA32: 0.3 | AB32: RPC <3.33 | AC32: RPC 3.33 sd. 4.50 | AD32: RPC >4.50 sd. 6.50 | AE32: RPC >6.50
I33: =AD19 | P33: : | Q33: =Q34-Q32 | AA33: 0.35 | AB33: RPC <2.86 | AC33: RPC 2.86 sd. 4.25 | AD33: RPC >4.25 sd. 6.50 | AE33: RPC >6.50
I34: =AE19 | P34: : | Q34: =N27*J54 | AA34: 0.4 | AB34: RPC <2.50 | AC34: RPC 2.50 sd. 4 | AD34: RPC >4 sd. 6 | AE34: RPC >6
I35: Angsuran/Bulan I | P35: : | Q35: =Q34/J54 | AA35: =N25 | AB35: =AA31/AA35
A37: Plafond yang Diajukan | AA37: =B74 | AB37: =VLOOKUP(AA35,AA31:AE34,3,0)
I38: =AC19 | P38: : | Q38: =N17
I39: =AD19 | P39: : | Q39: =Q38*N18*N19 | AA39: 0.4 | AB39: =IF($AA$37<2.5,"RPC <2.50",IF(AND($AA$37>=2.5,$AA$37<=4),"RPC 2.50 sd. 4",IF(AND($AA$37>4,$AA$37<=6),"RPC >4 sd. 6",IF($AA$37>6,"RPC >6")))) | AC39: =IF($AA$37<2.5,AB34,IF(AND($AA$37>=2.5,$AA$37<=4),AC34,IF(AND($AA$37>4,$AA$37<=6),AD34,IF($AA$37>6,AE34))))
I40: =AE19 | P40: : | Q40: =SUM(Q38:S39) | AA40: 0.35 | AB40: =IF($AA$37<2.86,"RPC <2.86",IF(AND($AA$37>=2.86,$AA$37<=4.25),"RPC 2.86 sd. 4.25",IF(AND($AA$37>4.25,$AA$37<=6.5),"RPC >4.25 sd. 6.50",IF($AA$37>6.5,"RPC >6.50")))) | AC40: =IF($AA$37<2.86,AB33,IF(AND($AA$37>=2.86,$AA$37<=4.25),AC33,IF(AND($AA$37>4.25,$AA$37<=6.5),AD33,IF($AA$37>6.5,AE33))))
I41: Angsuran/Bulan II | P41: : | Q41: =Q40/N19 | AA41: 0.3 | AB41: =IF($AA$37<3.33,"RPC <3.33",IF(AND($AA$37>=3.33,$AA$37<=4.5),"RPC 3.33 sd. 4.50",IF(AND($AA$37>4.5,$AA$37<=6.5),"RPC >4 sd. 6.50",IF($AA$37>6.5,"RPC >6.50")))) | AC41: =IF($AA$37<3.33,AB32,IF(AND($AA$37>=3.33,$AA$37<=4.5),AC32,IF(AND($AA$37>4.5,$AA$37<=6.5),AD32,IF($AA$37>6.5,AE32))))
I42: Surplus Cashflow | P42: : | Q42: =N27-Q41
AF45: =IF(AE58=0,0,AE56)
A47: USULAN PEMBIAYAAN
N48: =IF(Parameter!G32<=2,'Usulan Pembiayaan'!AC48,'Usulan Pembiayaan'!AC49) | AA48: =Parameter!H253 | AB48: =AA48*12 | AC48: =IF(J54>AB48,"Jangka Waktu Melebihi Usia Pensiun","")
B49: =$AF$19 | I49: : | AA49: =Parameter!H254 | AB49: =AA49*12 | AC49: =IF(J54>AB49,"Jangka Waktu > Usia Pensiun","")
B50: =$AG$19 | I50: : | M50: =AB52 | AB50: Sudah diserahkan kepada penjual, bukti pembayaran/kwitansi terlampir
B51: =$AH$19 | I51: : | AB51: =IF(AB19="Murabahah",AB50,"")
B52: =$AI$19 | I52: : | AB52: =IF(J50>0,AB51,"")
B53: =$AJ$19 | I53: : | J53: =AO19 | AB53: min | AC53: mid | AD53: max
B54: Jangka Waktu | I54: : | M54: Bulan | AA54: ='Aspek Keuangan'!M5+'Aspek Keuangan'!M65 | AB54: =AA58 | AC54: =AB54+AC22 | AD54: =AC54+AD22
B55: =AL19 | I55: : | S55: ="Setara Margin "&Jadang!R25&" Per Bulan:" | T55: =IF(M55="Flat",Jadang!Q37,Jadang!P37) | AA55: =('Aspek Keuangan'!M5*60%)+('Aspek Keuangan'!M65*20%) | AB55: ="RPC "&"<"&AB54 | AC55: ="RPC "&AB54&" sd. "&AC54 | AD55: ="RPC>"&AC54&" sd. "&AD54 | AE55: ="RPC>"&AD54
B56: =AD19 | I56: : | J56: =IF(M55="Flat",Jadang!U129,Jadang!X129) | S56: Per Tahun: | T56: =IF(M55="Flat",Jadang!Q38,Jadang!P38) | AA56: =AA54/AA55 | AB56: 0 | AC56: 9 | AD56: 13.5 | AE56: 18
B57: =AE19 | I57: : | J57: =J56+J53 | AA57: =N26+J60 | AB57: =IF(AA59<AB54,AB55,0) | AC57: =IF(AND(AA59>=AB54,AA59<=AC54),AC55,0) | AD57: =IF(AND(AA59>AC54,AA59<=AD54),AD55,0) | AE57: =IF(AA59>AD54,AE55,0)
B58: =AK19 | I58: : | J58: =Jadang!E8 | AA58: =AA56 | AB58: =IF(AB57=0,0,1) | AC58: =IF(AC57=0,0,1) | AD58: =IF(AD57=0,0,1) | AE58: =IF(AE57=0,0,1)
B59: =AM19 | I59: : | J59: =Jadang!D8 | AA59: =AA54/(N26+J60) | AF59: =IF(AB58=0,0,AB56)
B60: =AN19 | I60: : | J60: =J57/J54 | AF60: =IF(AC58=0,0,AC56)
B61: =AP19 | I61: : | J61: =N27-J60 | AF61: =IF(AD58=0,0,AD56)
AF62: =IF(AE58=0,0,AE56)
A63: AGUNAN | AA63: ='Informasi Pokok'!D32
A65: Persentase Agunan terhadap Pembiayaan | I65: : | J65: ='Aspek Non Keuangan'!I62/J53 | L65: ="Persentase Agunan "&Parameter!T120 | AA65: =IF(AA63="Potong Gaji Langsung",1,2) | AB65: 1 | AC65: Tanpa Agunan/Potong Gaji Langsung
AB66: 2
A68: HASIL SKORING | AA68: =VLOOKUP(AA35,AA39:AC41,3,0)
B70: SCORE | E70: RATING | G70: STATUS | J70: =IFERROR(VLOOKUP(E71,Rating!E4:I23,5,0),"Unrated") | AB70: =VLOOKUP($AA$35,$AA$32:$AE$34,2,0) | AC70: 1
B71: =Parameter!U143 | E71: =IFERROR(VLOOKUP(ROUND(B71,0),Rating!$D$26:$F$126,2,0),"Unrated") | G71: =IF(B71="unrated","input Error",IF(B71>=70,"Layak","Tidak Layak")) | AB71: =VLOOKUP($AA$35,$AA$32:$AE$34,3,0) | AC71: 5
AB72: =VLOOKUP($AA$35,$AA$32:$AE$34,4,0) | AC72: 7
B73: Repayment Capacity | AB73: =VLOOKUP($AA$35,$AA$32:$AE$34,5,0) | AC73: 10
B74: =AA59 | E74: =AD81
A77: * Penyesuaian/Adjustment | AD77: =VLOOKUP(AA68,AB70:AC73,2,0)
B79: Selain potong gaji pemohon menjaminkan aset sebagai berikut :
B80: 1
B81: 2 | AA81: =IF(B74>=AA58,"Memadai","Tidak Memadai") | AB81: =IF(AA81="Memadai",1,2) | AC81: =MAX(AB81:AB82) | AD81: =IF(AC81=1,"Memadai","Tidak Memadai")
AB82: =IF(N48="Jangka Waktu > Usia Pensiun",2,1)
A84: VERIFIKASI
J86: Mengetahui | P86: Pengusul,
P90: ='Informasi Pokok'!D5
J91: Koord Marketing | P91: Account Officer
B94: ='Aspek Non Keuangan'!H101 | K94: Merekomendasikan | Q94: Tidak Merekomendasikan
B101: (......................................)
B103: ='Aspek Non Keuangan'!H109 | K103: Menyetujui | Q103: Tidak Menyetujui
B110: (...................................)

Sheet K Modal
B2: PERPUTARAN MODAL KERJA
Y3: Kebutuhan Modal Kerja | AB3: Kebutuhan Modal Kerja Berdasakan Perputaran Usaha
B4: Perputaran Kas | H4: : | I4: Δ | J4: Penjualan | M4: = | N4: ='Usulan Pembiayaan'!N24:Q24 | S4: = | T4: =N4/N5 | V4: kali | Y4: Tranding Asset | Z4: =+N17+N11 | AB4: Perputaran Persediaan | AC4: =+N17*30/N4
J5: Kas | N5: ='Aspek Keuangan'!#REF! | Y5: SF | Z5: ='Aspek Keuangan'!#REF! | AB5: Perputaran Piutang | AC5: =+N11*30/N4
Y6: Kebutuhan Modal | Z6: =+Z4-Z5 | AB6: Perputaran Utang | AC6: =('Aspek Keuangan'!#REF!+200000000)*30/N4
I7: Δ | J7: HARI | L7: = | M7: 30 | O7: = | P7: =M7/M8 | R7: hari | Y7: PM 15% | Z7: ='Aspek Keuangan'!#REF!*Z6 | AB7: NTC | AC7: =+(AC4+AC5)-AC6
M8: =T4 | Y8: Kebutuhan Modal Kerja Netto | Z8: =+Z6-Z7 | AB8: Kebutuhan Modal Kerja Netto | AC8: =((1-(100%-85%))*((N4*AC7)/30))
Y9: 1.1 | Z9: =Z8*Y9 | AC9: =S34-AC8
B10: Perputaran Piutang | H10: : | I10: Δ | J10: Penjualan | M10: = | N10: =N4 | S10: = | T10: =N10/N11 | V10: kali | AC10: =AC9/S34
J11: Piutang | N11: ='Aspek Keuangan'!#REF!
I13: Δ | J13: HARI | L13: = | M13: 30 | O13: = | P13: =M13/M14 | R13: hari
M14: =T10 | Y14: =N4*85%
B16: Perputaran Persediaan | H16: : | I16: Δ | J16: HPP | M16: = | N16: =Y14 | S16: = | T16: =N16/N17 | V16: kali
J17: Persediaan | N17: ='Aspek Keuangan'!#REF!
I19: Δ | J19: HARI | L19: = | M19: 30 | O19: = | P19: =M19/M20 | R19: hari
M20: =T16
B23: Proyeksi Kas | G23: : | H23: =P7 | J23: X | K23: =N4 | O23: X | P23: 1 | R23: = | S23: =(H23*K23/H24)*P23
H24: 30
B26: Proyeksi Piutang | G26: : | H26: =P13 | J26: X | K26: =N10 | O26: X | P26: 1.2 | R26: = | S26: =(K26*H26/H27)*P26
H27: 30
B29: Proyeksi Persediaan | G29: : | H29: =P19 | J29: X | K29: =N16 | O29: X | P29: 1.2 | R29: = | S29: =(K29*H29/H30)*P29
H30: 30
B32: Jumlah Proyeksi Modal kerja | S32: =S23+S26+S29
B34: Modal Kerja Bersih | S34: =N17+N11+N5 | W34: (-)
S35: =S32-S34
B36: Kebutuhan Kredit
B38: Hutang Dagang
B40: Hutang Bank | L40: (+)
S41: =H38+H40 | W41: (+)
B43: Total Kebutuhan Kredit | S43: =S35+S41

Sheet Komite Kredit
A1: KEPUTUSAN KREDIT
R3: Tanggal | U3: =TODAY()
A4: A. | B4: DATA DEBITUR
B5: - | C5: Nama Debitur | I5: : | J5: ='Informasi Pokok'!D11
B6: - | C6: Alamat Debitur | I6: : | J6: ='Informasi Pokok'!D15
B7: - | C7: Pekerjaan | I7: :
A9: B. | B9: FASILITAS KREDIT
B10: - | C10: ='Usulan Pembiayaan'!B15 | I10: : | J10: ='Usulan Pembiayaan'!N15 | O10: - | P10: Gol Debitur | U10: : | V10: 875
B11: - | C11: ='Usulan Pembiayaan'!#REF! | I11: : | J11: ='Usulan Pembiayaan'!#REF! | O11: - | P11: Sifat kredit | U11: : | V11: 3
B12: - | C12: ='Usulan Pembiayaan'!#REF! | I12: : | J12: ='Usulan Pembiayaan'!#REF! | O12: - | P12: Jenis Penggunaan | U12: : | V12: 10
B13: - | C13: ='Usulan Pembiayaan'!#REF! | I13: : | J13: ='Usulan Pembiayaan'!#REF! | O13: - | P13: Sektor Ekonomi | U13: : | V13: 1007
B14: - | C14: ='Usulan Pembiayaan'!#REF! | I14: : | J14: ='Usulan Pembiayaan'!#REF! | O14: - | P14: Hub. dengan Bank | U14: : | V14: 02
B15: - | C15: ='Usulan Pembiayaan'!#REF! | I15: : | J15: ='Usulan Pembiayaan'!#REF!
A17: C. | B17: JAMINAN
B18: No | C18: Jenis Agunan | K18: Pengikatan | N18: Nilai Pasar | R18: % | S18: Nilai | W18: Nilai HT
B19: 1 | K19: ='Aspek Non Keuangan'!#REF! | N19: ='Aspek Non Keuangan'!#REF! | R19: 0.8 | S19: ='Aspek Non Keuangan'!#REF! | W19: ='Aspek Non Keuangan'!#REF!
B20: 2 | K20: ='Aspek Non Keuangan'!#REF! | N20: ='Aspek Non Keuangan'!#REF! | R20: 0.6 | S20: ='Aspek Non Keuangan'!#REF! | W20: ='Aspek Non Keuangan'!#REF!
B21: 3 | K21: ='Aspek Non Keuangan'!#REF! | N21: ='Aspek Non Keuangan'!#REF! | R21: 0.6 | S21: ='Aspek Non Keuangan'!#REF! | W21: ='Aspek Non Keuangan'!#REF!
B22: Total | N22: =SUM(N19:Q21) | S22: =SUM(S19:V21) | W22: =SUM(W19:Z21)
B23: Keterangan :
A27: D. | B27: PENGIKATAN
B28: - | C28: Pengikatan Kredit diikat Secara | L28: : | M28: Notaril
B29: - | C29: Daftar Asuransi Jiwa | L29: : | M29: Didaftarkan
B30: - | C30: Agunan Kendaraan | L30: : | M30: Diasuransikan (minimal TLO)
A32: Demikian, Keputusan Komite Kredit ini dibuat sebagai pedoman keputusan pemberian kredit.
A34: Pemutus Kredit Non Limit
A35: Area Manager
AC39: 3241250
A40: Pemutus Kredit Non Limit | AC40: 874500
A41: Direktur Operasional | AC41: =+AC39-AC40
AC42: 955556 | AD42: =+AC41/AC42
AC43: =+AC41-AC42
A46: Pemutus Kredit Pemegang Limit
A47: Direktur Utama

Sheet Keputusan Pembiayaan
A2: MEMO KEPUTUSAN PEMBIAYAAN
A6: PERMOHONAN YANG DIAJUKAN
A8: 1 | B8: No. MUP | L8: : | N8: =" "&'Informasi Pokok'!D3 -> 021/Reg/BS-AR/V/2025
A9: 2 | B9: Kantor | L9: : | N9: ='Informasi Pokok'!D2
A10: 3 | B10: Nama Account Officer | L10: : | N10: ='Informasi Pokok'!D5
A11: 4 | B11: Nama Pemohon | L11: : | N11: ='Informasi Pokok'!D11
A12: 5 | B12: Akad Pembiayaan | L12: : | N12: ='Informasi Pokok'!D58
A13: 6 | B13: Jenis Penggunaan | L13: : | N13: ='Informasi Pokok'!D60
A14: 7 | B14: Jumlah Permohonan | L14: : | N14: ='Informasi Pokok'!D55
A15: 8 | B15: Jangka Waktu | L15: : | N15: ='Usulan Pembiayaan'!N19&" Bulan"
A16: 9 | B16: Expected Return/Bulan | L16: : | N16: ='Usulan Pembiayaan'!N18 | R16: ='Usulan Pembiayaan'!R18
A17: 10 | B17: Agsuran Perbulan | L17: : | N17: ='Usulan Pembiayaan'!N20
A19: HASIL SCORING DEBITUR
A20: A | B20: INFORMASI DASAR
B21: a. Jenis Kategori Nasabah | M21: ='Informasi Pokok'!D10
B22: b. Jenis Kelamin | M22: ='Informasi Pokok'!D12
B23: c. Usia | M23: ='Informasi Pokok'!I14
B24: d. Status Perkawinan | M24: ='Informasi Pokok'!D21
B25: e. Jumlah Tanggungan | M25: ='Informasi Pokok'!D22
B26: f. Tingkat Pendidikan | M26: ='Informasi Pokok'!D23
B27: g. Kepemilikan Tempat Tinggal | M27: ='Informasi Pokok'!D24
B28: h. Status Karyawan | M28: ='Informasi Pokok'!D25
B29: i. Bidang Usaha Pekerjaan | M29: ='Informasi Pokok'!D26
B30: j. Bonafiditas Perusahaan | M30: ='Informasi Pokok'!D27
B31: k. Usia Pensiun | M31: ='Informasi Pokok'!D28&" Tahun"
B32: l. Surat Keterangan Bekerja | M32: ='Informasi Pokok'!D29
B33: m. Slip Gaji | M33: ='Informasi Pokok'!D30
B34: n. Rekening Gaji | M34: ='Informasi Pokok'!D31
B35: o. Reputasi di Tempat Bekerja dan Tempat Tinggal | M35: ='Informasi Pokok'!D34
A36: B | B36: HUBUNGAN DENGAN BANK
B37: a. Hubungan Dengan Perbankan | M37: ='Informasi Pokok'!D48
B38: b. Riwayat Pembiayaan Bank (SLIK) | M38: ='Informasi Pokok'!D49
A39: C | B39: KAPASITAS MEMBAYAR PINJAMAN
B40: a. Jangka Waktu Pembiayaan | M40: =Parameter!T110
B41: b. Repayment Capacity (RPC) | M41: =TEXT('Usulan Pembiayaan'!B74,"#.##")&" ("&('Usulan Pembiayaan'!E74)&")"
B42: c. Permohonan Pembiayaan Ke- | M42: ='Informasi Pokok'!E53
A43: D | B43: AGUNAN | AB43: ='Aspek Non Keuangan'!#REF!
B44: a. Persentase Agunan | M44: =Parameter!T120
B45: b. Pengikatan Agunan | M45: ='Aspek Non Keuangan'!K77
A46: E | B46: ASURANSI | AB46: ='Aspek Non Keuangan'!#REF!
B47: a. Asuransi Jiwa | M47: ='Aspek Non Keuangan'!F83
B48: b. Asuransi Agunan | M48: ='Aspek Non Keuangan'!F88&" "&'Aspek Non Keuangan'!K88
A49: F | B49: RISIKO NASABAH
B50: - Tingkat Risiko Nasabah | M50: =Parameter!T96
A52: KEPUTUSAN PEMBIAYAAN
B55: 1. | C55: Akad Pembiayaan | J55: : | K55: =N12
B56: 2. | C56: Jenis Penggunaan | J56: : | K56: =N13
B57: 3. | C57: Jangka Waktu | J57: : | K57: ='Usulan Pembiayaan'!J54 | M57: Bulan
B58: 4. | C58: ='Usulan Pembiayaan'!B55 | J58: : | K58: ='Usulan Pembiayaan'!J55 | Q58: ='Usulan Pembiayaan'!M55
B59: 5. | C59: ='Usulan Pembiayaan'!B49 | J59: : | K59: ='Usulan Pembiayaan'!J49
B60: 6. | C60: ='Usulan Pembiayaan'!B50 | J60: : | K60: ='Usulan Pembiayaan'!J50 | Q60: =IF('Usulan Pembiayaan'!M50="","",'Usulan Pembiayaan'!M50)
B61: 7. | C61: ='Usulan Pembiayaan'!B51 | J61: : | K61: ='Usulan Pembiayaan'!J51
B62: 8. | C62: ='Usulan Pembiayaan'!B52 | J62: : | K62: ='Usulan Pembiayaan'!J52
B63: 9. | C63: ='Usulan Pembiayaan'!B53 | J63: : | K63: ='Usulan Pembiayaan'!J53
B64: 10. | C64: ='Usulan Pembiayaan'!B56 | J64: : | K64: ='Usulan Pembiayaan'!J56
B65: 11. | C65: ='Usulan Pembiayaan'!B57 | J65: : | K65: ='Usulan Pembiayaan'!J57
B66: 12. | C66: ='Usulan Pembiayaan'!B58 | J66: : | K66: ='Usulan Pembiayaan'!J58
B67: 13. | C67: ='Usulan Pembiayaan'!B59 | J67: : | K67: ='Usulan Pembiayaan'!J59
B68: 14. | C68: ='Usulan Pembiayaan'!B60 | J68: : | K68: ='Usulan Pembiayaan'!J60
C71: Pengusul | K71: Menyetujui,
C76: Account Officer | K76: Koord. Marketing | R76: Kabag. Marketing

Sheet Rekomendasi AO
A1: REKOMENDASI USULAN PEMBIAYAAN
A2: Dari Kesimpulan tersebut maka calon Pemohon dapat direkomendasikan
A3: untuk mendpatkan pembiayaan sebagai berikut:
A4: - | B4: Nama | C4: : | D4: ='Informasi Pokok'!D11:J11
A5: - | B5: Maksimal Plaffond | C5: :
A6: - | B6: Harga Jual | C6: : | D6: =F11*D7+D5
A7: - | B7: Jangka Waktu | C7: : | E7: Bulan
A8: - | B8: Akad | C8: :
A9: - | B9: Tujuan Penggunaan | C9: :
A10: - | B10: Angsuran Pokok | C10: : | F10: =D5/D7
A11: - | B11: Angsuran Margin | C11: : | F11: =D5*D19
A12: - | B12: Angsuran Per bulan | C12: : | D12: =F10+F11
B13: Angsuran Per tgl 10 | C13: : | D13: =D12/2
B14: Angsuran Per tgl 25 | C14: : | D14: =D13
A15: - | B15: Biaya Asuransi | C15: :
A16: - | B16: Biaya Notaris | C16: :
A17: - | B17: Biaya ADM | C17: : | D17: =D5*2.5%
A18: - | B18: Tabungan Blokiran | C18: : | D18: =D12
A19: - | B19: Rate | C19: :
A20: - | B20: Skema Angsuran | C20: :
A24: Pengusul | D24: Menyetujui,
A29: Account Officer | D29: Koord. Marketing | G29: Kabag. Marketing

Sheet Jadang
A1: ="JADWAL ANGSURAN AKAD "&'Keputusan Pembiayaan'!N12&" ("&Q25&")" | H1: ="JADWAL ANGSURAN AKAD "&'Keputusan Pembiayaan'!N12&" ("&R25&")" | W1: 1,5% flat = 0,83% Efektif | Z1: =0.83*12 | AA1: =1.5*12
A2: ="Atas Nama "&'Keputusan Pembiayaan'!N11 | H2: ="Atas Nama "&'Keputusan Pembiayaan'!N11 | P2: =Q26 | W2: 1,5% efektif = 2,64% Flat | Z2: 1.15 | AA2: 1.83 | AB2: =AA2-Z2
B3: ='Informasi Pokok'!D6 | I3: 1
C4: Os. Pokok | D4: Pokok | E4: Margin | J4: OS. Pokok | K4: Pokok | L4: Margin | P4: Flat | Q4: jw | R4: =Q27 | Z4: =Z2*12 | AB4: =AA2*12 | AC4: =AB4-Z4 | AD4: =AC4/12
A5: No. | B5: Tanggal | F5: Total Angsuran | H5: No. | I5: Tanggal | M5: Total Angsuran | P5: Efektif | Q5: flat | R5: =P37 | T5: Flat | V5: Efektif
Q6: efektif | R6: =Q38 | T6: Pokok | U6: Margin | W6: Pokok | X6: margin | Y6: total
A8: 1 | B8: =IF(B3="","",DATE(YEAR(B3),MONTH(B3)+1,DAY(B3))) | C8: =P2 | D8: =IF('Usulan Pembiayaan'!$M$55="Flat",T8,W8)+67 | E8: =IF('Usulan Pembiayaan'!$M$55="Flat",U8,X8) | F8: =D8+E8 | H8: 1 | I8: =B8 | J8: =P2 | K8: =IF('Usulan Pembiayaan'!$M$55="Flat",W8,T8) | L8: =IF('Usulan Pembiayaan'!$M$55="Flat",X8,U8) | M8: =K8+L8+67 | P8: =PMT(R6%/12,R4,-P2,2) | Q8: 2200000 | T8: =(ROUNDDOWN(P2/R4,1)) | U8: =P2*R5 | V8: =P2 | W8: =Y8-X8 | X8: =(ROUNDDOWN(V8*$R$6/12,1)) | Y8: =PMT(R6/12,R4,-P2)
A9: 2 | B9: =IF(B8="","",DATE(YEAR(B8),MONTH(B8)+1,DAY(B8))) | C9: =C8-D8 | D9: =IF('Usulan Pembiayaan'!$M$55="Flat",T9,W9)+67 | E9: =IF('Usulan Pembiayaan'!$M$55="Flat",U9,X9) | F9: =D9+E9 | H9: 2 | I9: =IF(I8="","",DATE(YEAR(I8),MONTH(I8)+1,DAY(I8))) | J9: =J8-K8 | K9: =IF('Usulan Pembiayaan'!$M$55="Flat",W9,T9) | L9: =IF('Usulan Pembiayaan'!$M$55="Flat",X9,U9) | M9: =K9+L9+67 | P9: =(P2+U129)/R4 | Q9: 2034425.7 | T9: =IF(A9<=$R$4,$P$2/$R$4,0) | U9: =IF(A9<=$R$4,$U$8,0) | V9: =IF(A9<=$R$4,V8-W8,0) | W9: =Y9-X9 | X9: =IF(A9<=$R$4,V9*$R$6/12,0) | Y9: =IF(A9<=$R$4,$Y$8,0)
A10: 3 | B10: =IF(B9="","",DATE(YEAR(B9),MONTH(B9)+1,DAY(B9))) | C10: =C9-D9 | D10: =IF('Usulan Pembiayaan'!$M$55="Flat",T10,W10)+67 | E10: =IF('Usulan Pembiayaan'!$M$55="Flat",U10,X10) | F10: =D10+E10 | H10: 3 | I10: =IF(I9="","",DATE(YEAR(I9),MONTH(I9)+1,DAY(I9))) | J10: =J9-K9 | K10: =IF('Usulan Pembiayaan'!$M$55="Flat",W10,T10) | L10: =IF('Usulan Pembiayaan'!$M$55="Flat",X10,U10) | M10: =K10+L10+67 | P10: =P9-P8 | Q10: 1865815.8 | T10: =IF(A10<=$R$4,$P$2/$R$4,0) | U10: =IF(A10<=$R$4,$U$8,0) | V10: =IF(A10<=$R$4,V9-W9,0) | W10: =Y10-X10 | X10: =IF(A10<=$R$4,V10*$R$6/12,0) | Y10: =IF(A10<=$R$4,$Y$8,0)
A11: 4 | B11: =IF(B10="","",DATE(YEAR(B10),MONTH(B10)+1,DAY(B10))) | C11: =C10-D10 | D11: =IF('Usulan Pembiayaan'!$M$55="Flat",T11,W11)+67 | E11: =IF('Usulan Pembiayaan'!$M$55="Flat",U11,X11) | F11: =D11+E11 | H11: 4 | I11: =IF(I10="","",DATE(YEAR(I10),MONTH(I10)+1,DAY(I10))) | J11: =J10-K10 | K11: =IF('Usulan Pembiayaan'!$M$55="Flat",W11,T11) | L11: =IF('Usulan Pembiayaan'!$M$55="Flat",X11,U11) | M11: =K11+L11+67 | Q11: 1694114.8 | T11: =IF(A11<=$R$4,$P$2/$R$4,0) | U11: =IF(A11<=$R$4,$U$8,0) | V11: =IF(A11<=$R$4,V10-W10,0) | W11: =Y11-X11 | X11: =IF(A11<=$R$4,V11*$R$6/12,0) | Y11: =IF(A11<=$R$4,$Y$8,0)
A12: 5 | B12: =IF(B11="","",DATE(YEAR(B11),MONTH(B11)+1,DAY(B11))) | C12: =C11-D11 | D12: =IF('Usulan Pembiayaan'!$M$55="Flat",T12,W12)+67 | E12: =IF('Usulan Pembiayaan'!$M$55="Flat",U12,X12) | F12: =D12+E12 | H12: 5 | I12: =IF(I11="","",DATE(YEAR(I11),MONTH(I11)+1,DAY(I11))) | J12: =J11-K11 | K12: =IF('Usulan Pembiayaan'!$M$55="Flat",W12,T12) | L12: =IF('Usulan Pembiayaan'!$M$55="Flat",X12,U12) | M12: =K12+L12+67 | P12: =X129 | Q12: 1519266 | T12: =IF(A12<=$R$4,$P$2/$R$4,0) | U12: =IF(A12<=$R$4,$U$8,0) | V12: =IF(A12<=$R$4,V11-W11,0) | W12: =Y12-X12 | X12: =IF(A12<=$R$4,V12*$R$6/12,0) | Y12: =IF(A12<=$R$4,$Y$8,0)
A13: 6 | B13: =IF(B12="","",DATE(YEAR(B12),MONTH(B12)+1,DAY(B12))) | C13: =C12-D12 | D13: =IF('Usulan Pembiayaan'!$M$55="Flat",T13,W13)+67 | E13: =IF('Usulan Pembiayaan'!$M$55="Flat",U13,X13) | F13: =D13+E13 | H13: 6 | I13: =IF(I12="","",DATE(YEAR(I12),MONTH(I12)+1,DAY(I12))) | J13: =J12-K12 | K13: =IF('Usulan Pembiayaan'!$M$55="Flat",W13,T13) | L13: =IF('Usulan Pembiayaan'!$M$55="Flat",X13,U13) | M13: =K13+L13+67 | P13: =P12/P2*100/R4 | Q13: 1341211.5 | T13: =IF(A13<=$R$4,$P$2/$R$4,0) | U13: =IF(A13<=$R$4,$U$8,0) | V13: =IF(A13<=$R$4,V12-W12,0) | W13: =Y13-X13 | X13: =IF(A13<=$R$4,V13*$R$6/12,0) | Y13: =IF(A13<=$R$4,$Y$8,0)
A14: 7 | B14: =IF(B13="","",DATE(YEAR(B13),MONTH(B13)+1,DAY(B13))) | C14: =C13-D13 | D14: =IF('Usulan Pembiayaan'!$M$55="Flat",T14,W14)+67 | E14: =IF('Usulan Pembiayaan'!$M$55="Flat",U14,X14) | F14: =D14+E14 | H14: 7 | I14: =IF(I13="","",DATE(YEAR(I13),MONTH(I13)+1,DAY(I13))) | J14: =J13-K13 | K14: =IF('Usulan Pembiayaan'!$M$55="Flat",W14,T14) | L14: =IF('Usulan Pembiayaan'!$M$55="Flat",X14,U14) | M14: =K14+L14+67 | Q14: 1159892.8 | T14: =IF(A14<=$R$4,$P$2/$R$4,0) | U14: =IF(A14<=$R$4,$U$8,0) | V14: =IF(A14<=$R$4,V13-W13,0) | W14: =Y14-X14 | X14: =IF(A14<=$R$4,V14*$R$6/12,0) | Y14: =IF(A14<=$R$4,$Y$8,0)
A15: 8 | B15: =IF(B14="","",DATE(YEAR(B14),MONTH(B14)+1,DAY(B14))) | C15: =C14-D14 | D15: =IF('Usulan Pembiayaan'!$M$55="Flat",T15,W15)+67 | E15: =IF('Usulan Pembiayaan'!$M$55="Flat",U15,X15) | F15: =D15+E15 | H15: 8 | I15: =IF(I14="","",DATE(YEAR(I14),MONTH(I14)+1,DAY(I14))) | J15: =J14-K14 | K15: =IF('Usulan Pembiayaan'!$M$55="Flat",W15,T15) | L15: =IF('Usulan Pembiayaan'!$M$55="Flat",X15,U15) | M15: =K15+L15+67 | P15: =U129 | Q15: 975249.8 | T15: =IF(A15<=$R$4,$P$2/$R$4,0) | U15: =IF(A15<=$R$4,$U$8,0) | V15: =IF(A15<=$R$4,V14-W14,0) | W15: =Y15-X15 | X15: =IF(A15<=$R$4,V15*$R$6/12,0) | Y15: =IF(A15<=$R$4,$Y$8,0)
A16: 9 | B16: =IF(B15="","",DATE(YEAR(B15),MONTH(B15)+1,DAY(B15))) | C16: =C15-D15 | D16: =IF('Usulan Pembiayaan'!$M$55="Flat",T16,W16)+67 | E16: =IF('Usulan Pembiayaan'!$M$55="Flat",U16,X16) | F16: =D16+E16 | H16: 9 | I16: =IF(I15="","",DATE(YEAR(I15),MONTH(I15)+1,DAY(I15))) | J16: =J15-K15 | K16: =IF('Usulan Pembiayaan'!$M$55="Flat",W16,T16) | L16: =IF('Usulan Pembiayaan'!$M$55="Flat",X16,U16) | M16: =K16+L16+67 | P16: =P15/P2*100/R4 | Q16: 787221.8 | T16: =IF(A16<=$R$4,$P$2/$R$4,0) | U16: =IF(A16<=$R$4,$U$8,0) | V16: =IF(A16<=$R$4,V15-W15,0) | W16: =Y16-X16 | X16: =IF(A16<=$R$4,V16*$R$6/12,0) | Y16: =IF(A16<=$R$4,$Y$8,0)
A17: 10 | B17: =IF(B16="","",DATE(YEAR(B16),MONTH(B16)+1,DAY(B16))) | C17: =C16-D16 | D17: =IF('Usulan Pembiayaan'!$M$55="Flat",T17,W17)+67 | E17: =IF('Usulan Pembiayaan'!$M$55="Flat",U17,X17) | F17: =D17+E17 | H17: 10 | I17: =IF(I16="","",DATE(YEAR(I16),MONTH(I16)+1,DAY(I16))) | J17: =J16-K16 | K17: =IF('Usulan Pembiayaan'!$M$55="Flat",W17,T17) | L17: =IF('Usulan Pembiayaan'!$M$55="Flat",X17,U17) | M17: =K17+L17+67 | Q17: 595746.6 | T17: =IF(A17<=$R$4,$P$2/$R$4,0) | U17: =IF(A17<=$R$4,$U$8,0) | V17: =IF(A17<=$R$4,V16-W16,0) | W17: =Y17-X17 | X17: =IF(A17<=$R$4,V17*$R$6/12,0) | Y17: =IF(A17<=$R$4,$Y$8,0)
A18: 11 | B18: =IF(B17="","",DATE(YEAR(B17),MONTH(B17)+1,DAY(B17))) | C18: =C17-D17 | D18: =IF('Usulan Pembiayaan'!$M$55="Flat",T18,W18)+67 | E18: =IF('Usulan Pembiayaan'!$M$55="Flat",U18,X18) | F18: =D18+E18 | H18: 11 | I18: =IF(I17="","",DATE(YEAR(I17),MONTH(I17)+1,DAY(I17))) | J18: =J17-K17 | K18: =IF('Usulan Pembiayaan'!$M$55="Flat",W18,T18) | L18: =IF('Usulan Pembiayaan'!$M$55="Flat",X18,U18) | M18: =K18+L18+67 | Q18: 400760.9 | T18: =IF(A18<=$R$4,$P$2/$R$4,0) | U18: =IF(A18<=$R$4,$U$8,0) | V18: =IF(A18<=$R$4,V17-W17,0) | W18: =Y18-X18 | X18: =IF(A18<=$R$4,V18*$R$6/12,0) | Y18: =IF(A18<=$R$4,$Y$8,0)
A19: 12 | B19: =IF(B18="","",DATE(YEAR(B18),MONTH(B18)+1,DAY(B18))) | C19: =C18-D18 | D19: =IF('Usulan Pembiayaan'!$M$55="Flat",T19,W19)+67 | E19: =IF('Usulan Pembiayaan'!$M$55="Flat",U19,X19) | F19: =D19+E19 | H19: 12 | I19: =IF(I18="","",DATE(YEAR(I18),MONTH(I18)+1,DAY(I18))) | J19: =J18-K18 | K19: =IF('Usulan Pembiayaan'!$M$55="Flat",W19,T19) | L19: =IF('Usulan Pembiayaan'!$M$55="Flat",X19,U19) | M19: =K19+L19+67 | Q19: 202200.6 | T19: =IF(A19<=$R$4,$P$2/$R$4,0) | U19: =IF(A19<=$R$4,$U$8,0) | V19: =IF(A19<=$R$4,V18-W18,0) | W19: =Y19-X19 | X19: =IF(A19<=$R$4,V19*$R$6/12,0) | Y19: =IF(A19<=$R$4,$Y$8,0)
A20: 13 | B20: =IF(B19="","",DATE(YEAR(B19),MONTH(B19)+1,DAY(B19))) | C20: =C19-D19 | D20: =IF('Usulan Pembiayaan'!$M$55="Flat",T20,W20)+67 | E20: =IF('Usulan Pembiayaan'!$M$55="Flat",U20,X20) | F20: =D20+E20 | H20: 13 | I20: =IF(I19="","",DATE(YEAR(I19),MONTH(I19)+1,DAY(I19))) | J20: =J19-K19 | K20: =IF('Usulan Pembiayaan'!$M$55="Flat",W20,T20) | L20: =IF('Usulan Pembiayaan'!$M$55="Flat",X20,U20) | M20: =K20+L20+67 | T20: =IF(A20<=$R$4,$P$2/$R$4,0) | U20: =IF(A20<=$R$4,$U$8,0) | V20: =IF(A20<=$R$4,V19-W19,0) | W20: =Y20-X20 | X20: =IF(A20<=$R$4,V20*$R$6/12,0) | Y20: =IF(A20<=$R$4,$Y$8,0)
A21: 14 | B21: =IF(B20="","",DATE(YEAR(B20),MONTH(B20)+1,DAY(B20))) | C21: =C20-D20 | D21: =IF('Usulan Pembiayaan'!$M$55="Flat",T21,W21)+67 | E21: =IF('Usulan Pembiayaan'!$M$55="Flat",U21,X21) | F21: =D21+E21 | H21: 14 | I21: =IF(I20="","",DATE(YEAR(I20),MONTH(I20)+1,DAY(I20))) | J21: =J20-K20 | K21: =IF('Usulan Pembiayaan'!$M$55="Flat",W21,T21) | L21: =IF('Usulan Pembiayaan'!$M$55="Flat",X21,U21) | M21: =K21+L21+67 | T21: =IF(A21<=$R$4,$P$2/$R$4,0) | U21: =IF(A21<=$R$4,$U$8,0) | V21: =IF(A21<=$R$4,V20-W20,0) | W21: =Y21-X21 | X21: =IF(A21<=$R$4,V21*$R$6/12,0) | Y21: =IF(A21<=$R$4,$Y$8,0)
A22: 15 | B22: =IF(B21="","",DATE(YEAR(B21),MONTH(B21)+1,DAY(B21))) | C22: =C21-D21 | D22: =IF('Usulan Pembiayaan'!$M$55="Flat",T22,W22)+67 | E22: =IF('Usulan Pembiayaan'!$M$55="Flat",U22,X22) | F22: =D22+E22 | H22: 15 | I22: =IF(I21="","",DATE(YEAR(I21),MONTH(I21)+1,DAY(I21))) | J22: =J21-K21 | K22: =IF('Usulan Pembiayaan'!$M$55="Flat",W22,T22) | L22: =IF('Usulan Pembiayaan'!$M$55="Flat",X22,U22) | M22: =K22+L22+67 | T22: =IF(A22<=$R$4,$P$2/$R$4,0) | U22: =IF(A22<=$R$4,$U$8,0) | V22: =IF(A22<=$R$4,V21-W21,0) | W22: =Y22-X22 | X22: =IF(A22<=$R$4,V22*$R$6/12,0) | Y22: =IF(A22<=$R$4,$Y$8,0)
A23: 16 | B23: =IF(B22="","",DATE(YEAR(B22),MONTH(B22)+1,DAY(B22))) | C23: =C22-D22 | D23: =IF('Usulan Pembiayaan'!$M$55="Flat",T23,W23)+67 | E23: =IF('Usulan Pembiayaan'!$M$55="Flat",U23,X23) | F23: =D23+E23 | H23: 16 | I23: =IF(I22="","",DATE(YEAR(I22),MONTH(I22)+1,DAY(I22))) | J23: =J22-K22 | K23: =IF('Usulan Pembiayaan'!$M$55="Flat",W23,T23) | L23: =IF('Usulan Pembiayaan'!$M$55="Flat",X23,U23) | M23: =K23+L23+67 | T23: =IF(A23<=$R$4,$P$2/$R$4,0) | U23: =IF(A23<=$R$4,$U$8,0) | V23: =IF(A23<=$R$4,V22-W22,0) | W23: =Y23-X23 | X23: =IF(A23<=$R$4,V23*$R$6/12,0) | Y23: =IF(A23<=$R$4,$Y$8,0)
A24: 17 | B24: =IF(B23="","",DATE(YEAR(B23),MONTH(B23)+1,DAY(B23))) | C24: =C23-D23 | D24: =IF('Usulan Pembiayaan'!$M$55="Flat",T24,W24)+67 | E24: =IF('Usulan Pembiayaan'!$M$55="Flat",U24,X24) | F24: =D24+E24 | H24: 17 | I24: =IF(I23="","",DATE(YEAR(I23),MONTH(I23)+1,DAY(I23))) | J24: =J23-K23 | K24: =IF('Usulan Pembiayaan'!$M$55="Flat",W24,T24) | L24: =IF('Usulan Pembiayaan'!$M$55="Flat",X24,U24) | M24: =K24+L24+67 | P24: DATA | T24: =IF(A24<=$R$4,$P$2/$R$4,0) | U24: =IF(A24<=$R$4,$U$8,0) | V24: =IF(A24<=$R$4,V23-W23,0) | W24: =Y24-X24 | X24: =IF(A24<=$R$4,V24*$R$6/12,0) | Y24: =IF(A24<=$R$4,$Y$8,0)
A25: 18 | B25: =IF(B24="","",DATE(YEAR(B24),MONTH(B24)+1,DAY(B24))) | C25: =C24-D24 | D25: =IF('Usulan Pembiayaan'!$M$55="Flat",T25,W25)+67 | E25: =IF('Usulan Pembiayaan'!$M$55="Flat",U25,X25) | F25: =D25+E25 | H25: 18 | I25: =IF(I24="","",DATE(YEAR(I24),MONTH(I24)+1,DAY(I24))) | J25: =J24-K24 | K25: =IF('Usulan Pembiayaan'!$M$55="Flat",W25,T25) | L25: =IF('Usulan Pembiayaan'!$M$55="Flat",X25,U25) | M25: =K25+L25+67 | P25: Jenis Margin | Q25: ='Usulan Pembiayaan'!M55 | R25: =IF(Q25="Flat","Efektif","Flat") | T25: =IF(A25<=$R$4,$P$2/$R$4,0) | U25: =IF(A25<=$R$4,$U$8,0) | V25: =IF(A25<=$R$4,V24-W24,0) | W25: =Y25-X25 | X25: =IF(A25<=$R$4,V25*$R$6/12,0) | Y25: =IF(A25<=$R$4,$Y$8,0)
A26: 19 | B26: =IF(B25="","",DATE(YEAR(B25),MONTH(B25)+1,DAY(B25))) | C26: =C25-D25 | D26: =IF('Usulan Pembiayaan'!$M$55="Flat",T26,W26)+67 | E26: =IF('Usulan Pembiayaan'!$M$55="Flat",U26,X26) | F26: =D26+E26 | H26: 19 | I26: =IF(I25="","",DATE(YEAR(I25),MONTH(I25)+1,DAY(I25))) | J26: =J25-K25 | K26: =IF('Usulan Pembiayaan'!$M$55="Flat",W26,T26) | L26: =IF('Usulan Pembiayaan'!$M$55="Flat",X26,U26) | M26: =K26+L26+67 | P26: Plafond | Q26: ='Usulan Pembiayaan'!J53 | T26: =IF(A26<=$R$4,$P$2/$R$4,0) | U26: =IF(A26<=$R$4,$U$8,0) | V26: =IF(A26<=$R$4,V25-W25,0) | W26: =Y26-X26 | X26: =IF(A26<=$R$4,V26*$R$6/12,0) | Y26: =IF(A26<=$R$4,$Y$8,0)
A27: 20 | B27: =IF(B26="","",DATE(YEAR(B26),MONTH(B26)+1,DAY(B26))) | C27: =C26-D26 | D27: =IF('Usulan Pembiayaan'!$M$55="Flat",T27,W27)+67 | E27: =IF('Usulan Pembiayaan'!$M$55="Flat",U27,X27) | F27: =D27+E27 | H27: 20 | I27: =IF(I26="","",DATE(YEAR(I26),MONTH(I26)+1,DAY(I26))) | J27: =J26-K26 | K27: =IF('Usulan Pembiayaan'!$M$55="Flat",W27,T27) | L27: =IF('Usulan Pembiayaan'!$M$55="Flat",X27,U27) | M27: =K27+L27+67 | P27: Jangka Waktu | Q27: ='Usulan Pembiayaan'!J54 | T27: =IF(A27<=$R$4,$P$2/$R$4,0) | U27: =IF(A27<=$R$4,$U$8,0) | V27: =IF(A27<=$R$4,V26-W26,0) | W27: =Y27-X27 | X27: =IF(A27<=$R$4,V27*$R$6/12,0) | Y27: =IF(A27<=$R$4,$Y$8,0)
A28: 21 | B28: =IF(B27="","",DATE(YEAR(B27),MONTH(B27)+1,DAY(B27))) | C28: =C27-D27 | D28: =IF('Usulan Pembiayaan'!$M$55="Flat",T28,W28)+67 | E28: =IF('Usulan Pembiayaan'!$M$55="Flat",U28,X28) | F28: =D28+E28 | H28: 21 | I28: =IF(I27="","",DATE(YEAR(I27),MONTH(I27)+1,DAY(I27))) | J28: =J27-K27 | K28: =IF('Usulan Pembiayaan'!$M$55="Flat",W28,T28) | L28: =IF('Usulan Pembiayaan'!$M$55="Flat",X28,U28) | M28: =K28+L28+67 | P28: %Margin/bulan | Q28: ='Usulan Pembiayaan'!J55 | T28: =IF(A28<=$R$4,$P$2/$R$4,0) | U28: =IF(A28<=$R$4,$U$8,0) | V28: =IF(A28<=$R$4,V27-W27,0) | W28: =Y28-X28 | X28: =IF(A28<=$R$4,V28*$R$6/12,0) | Y28: =IF(A28<=$R$4,$Y$8,0)
A29: 22 | B29: =IF(B28="","",DATE(YEAR(B28),MONTH(B28)+1,DAY(B28))) | C29: =C28-D28 | D29: =IF('Usulan Pembiayaan'!$M$55="Flat",T29,W29)+67 | E29: =IF('Usulan Pembiayaan'!$M$55="Flat",U29,X29) | F29: =D29+E29 | H29: 22 | I29: =IF(I28="","",DATE(YEAR(I28),MONTH(I28)+1,DAY(I28))) | J29: =J28-K28 | K29: =IF('Usulan Pembiayaan'!$M$55="Flat",W29,T29) | L29: =IF('Usulan Pembiayaan'!$M$55="Flat",X29,U29) | M29: =K29+L29+67 | P29: Angsuran | Q29: =IF(Q25="Flat",((Q26/Q27)+(Q26*Q28)),PMT(Q28,Q27,-Q26)) | T29: =IF(A29<=$R$4,$P$2/$R$4,0) | U29: =IF(A29<=$R$4,$U$8,0) | V29: =IF(A29<=$R$4,V28-W28,0) | W29: =Y29-X29 | X29: =IF(A29<=$R$4,V29*$R$6/12,0) | Y29: =IF(A29<=$R$4,$Y$8,0)
A30: 23 | B30: =IF(B29="","",DATE(YEAR(B29),MONTH(B29)+1,DAY(B29))) | C30: =C29-D29 | D30: =IF('Usulan Pembiayaan'!$M$55="Flat",T30,W30)+67 | E30: =IF('Usulan Pembiayaan'!$M$55="Flat",U30,X30) | F30: =D30+E30 | H30: 23 | I30: =IF(I29="","",DATE(YEAR(I29),MONTH(I29)+1,DAY(I29))) | J30: =J29-K29 | K30: =IF('Usulan Pembiayaan'!$M$55="Flat",W30,T30) | L30: =IF('Usulan Pembiayaan'!$M$55="Flat",X30,U30) | M30: =K30+L30+67 | T30: =IF(A30<=$R$4,$P$2/$R$4,0) | U30: =IF(A30<=$R$4,$U$8,0) | V30: =IF(A30<=$R$4,V29-W29,0) | W30: =Y30-X30 | X30: =IF(A30<=$R$4,V30*$R$6/12,0) | Y30: =IF(A30<=$R$4,$Y$8,0)
A31: 24 | B31: =IF(B30="","",DATE(YEAR(B30),MONTH(B30)+1,DAY(B30))) | C31: =C30-D30 | D31: =IF('Usulan Pembiayaan'!$M$55="Flat",T31,W31)+67 | E31: =IF('Usulan Pembiayaan'!$M$55="Flat",U31,X31) | F31: =D31+E31 | H31: 24 | I31: =IF(I30="","",DATE(YEAR(I30),MONTH(I30)+1,DAY(I30))) | J31: =J30-K30 | K31: =IF('Usulan Pembiayaan'!$M$55="Flat",W31,T31) | L31: =IF('Usulan Pembiayaan'!$M$55="Flat",X31,U31) | M31: =K31+L31+67 | P31: KONVERSI | T31: =IF(A31<=$R$4,$P$2/$R$4,0) | U31: =IF(A31<=$R$4,$U$8,0) | V31: =IF(A31<=$R$4,V30-W30,0) | W31: =Y31-X31 | X31: =IF(A31<=$R$4,V31*$R$6/12,0) | Y31: =IF(A31<=$R$4,$Y$8,0)
A32: 25 | B32: =IF(B31="","",DATE(YEAR(B31),MONTH(B31)+1,DAY(B31))) | C32: =C31-D31 | D32: =IF('Usulan Pembiayaan'!$M$55="Flat",T32,W32)+67 | E32: =IF('Usulan Pembiayaan'!$M$55="Flat",U32,X32) | F32: =D32+E32 | H32: 25 | I32: =IF(I31="","",DATE(YEAR(I31),MONTH(I31)+1,DAY(I31))) | J32: =J31-K31 | K32: =IF('Usulan Pembiayaan'!$M$55="Flat",W32,T32) | L32: =IF('Usulan Pembiayaan'!$M$55="Flat",X32,U32) | M32: =K32+L32+67 | P32: Jenis Margin | Q32: =IF(Q25="Flat","Efektif","Flat") | T32: =IF(A32<=$R$4,$P$2/$R$4,0) | U32: =IF(A32<=$R$4,$U$8,0) | V32: =IF(A32<=$R$4,V31-W31,0) | W32: =Y32-X32 | X32: =IF(A32<=$R$4,V32*$R$6/12,0) | Y32: =IF(A32<=$R$4,$Y$8,0)
A33: 26 | B33: =IF(B32="","",DATE(YEAR(B32),MONTH(B32)+1,DAY(B32))) | C33: =C32-D32 | D33: =IF('Usulan Pembiayaan'!$M$55="Flat",T33,W33)+67 | E33: =IF('Usulan Pembiayaan'!$M$55="Flat",U33,X33) | F33: =D33+E33 | H33: 26 | I33: =IF(I32="","",DATE(YEAR(I32),MONTH(I32)+1,DAY(I32))) | J33: =J32-K32 | K33: =IF('Usulan Pembiayaan'!$M$55="Flat",W33,T33) | L33: =IF('Usulan Pembiayaan'!$M$55="Flat",X33,U33) | M33: =K33+L33+67 | P33: %Margin/bulan | Q33: =IF(Q32="Flat",((Q29/Q26)-(1/Q27)),RATE(Q27,Q29,-Q26)) | T33: =IF(A33<=$R$4,$P$2/$R$4,0) | U33: =IF(A33<=$R$4,$U$8,0) | V33: =IF(A33<=$R$4,V32-W32,0) | W33: =Y33-X33 | X33: =IF(A33<=$R$4,V33*$R$6/12,0) | Y33: =IF(A33<=$R$4,$Y$8,0)
A34: 27 | B34: =IF(B33="","",DATE(YEAR(B33),MONTH(B33)+1,DAY(B33))) | C34: =C33-D33 | D34: =IF('Usulan Pembiayaan'!$M$55="Flat",T34,W34)+67 | E34: =IF('Usulan Pembiayaan'!$M$55="Flat",U34,X34) | F34: =D34+E34 | H34: 27 | I34: =IF(I33="","",DATE(YEAR(I33),MONTH(I33)+1,DAY(I33))) | J34: =J33-K33 | K34: =IF('Usulan Pembiayaan'!$M$55="Flat",W34,T34) | L34: =IF('Usulan Pembiayaan'!$M$55="Flat",X34,U34) | M34: =K34+L34+67 | P34: Angsuran | Q34: =IF(Q32="Flat",((Q26/Q27)+(Q26*Q33)),IF(Q32="Efektif",PMT(Q33,Q27,-Q26))) | T34: =IF(A34<=$R$4,$P$2/$R$4,0) | U34: =IF(A34<=$R$4,$U$8,0) | V34: =IF(A34<=$R$4,V33-W33,0) | W34: =Y34-X34 | X34: =IF(A34<=$R$4,V34*$R$6/12,0) | Y34: =IF(A34<=$R$4,$Y$8,0)
A35: 28 | B35: =IF(B34="","",DATE(YEAR(B34),MONTH(B34)+1,DAY(B34))) | C35: =C34-D34 | D35: =IF('Usulan Pembiayaan'!$M$55="Flat",T35,W35)+67 | E35: =IF('Usulan Pembiayaan'!$M$55="Flat",U35,X35) | F35: =D35+E35 | H35: 28 | I35: =IF(I34="","",DATE(YEAR(I34),MONTH(I34)+1,DAY(I34))) | J35: =J34-K34 | K35: =IF('Usulan Pembiayaan'!$M$55="Flat",W35,T35) | L35: =IF('Usulan Pembiayaan'!$M$55="Flat",X35,U35) | M35: =K35+L35+67 | T35: =IF(A35<=$R$4,$P$2/$R$4,0) | U35: =IF(A35<=$R$4,$U$8,0) | V35: =IF(A35<=$R$4,V34-W34,0) | W35: =Y35-X35 | X35: =IF(A35<=$R$4,V35*$R$6/12,0) | Y35: =IF(A35<=$R$4,$Y$8,0)
A36: 29 | B36: =IF(B35="","",DATE(YEAR(B35),MONTH(B35)+1,DAY(B35))) | C36: =C35-D35 | D36: =IF('Usulan Pembiayaan'!$M$55="Flat",T36,W36)+67 | E36: =IF('Usulan Pembiayaan'!$M$55="Flat",U36,X36) | F36: =D36+E36 | H36: 29 | I36: =IF(I35="","",DATE(YEAR(I35),MONTH(I35)+1,DAY(I35))) | J36: =J35-K35 | K36: =IF('Usulan Pembiayaan'!$M$55="Flat",W36,T36) | L36: =IF('Usulan Pembiayaan'!$M$55="Flat",X36,U36) | M36: =K36+L36+67 | P36: FLAT | Q36: EFEKTIF | T36: =IF(A36<=$R$4,$P$2/$R$4,0) | U36: =IF(A36<=$R$4,$U$8,0) | V36: =IF(A36<=$R$4,V35-W35,0) | W36: =Y36-X36 | X36: =IF(A36<=$R$4,V36*$R$6/12,0) | Y36: =IF(A36<=$R$4,$Y$8,0)
A37: 30 | B37: =IF(B36="","",DATE(YEAR(B36),MONTH(B36)+1,DAY(B36))) | C37: =C36-D36 | D37: =IF('Usulan Pembiayaan'!$M$55="Flat",T37,W37)+67 | E37: =IF('Usulan Pembiayaan'!$M$55="Flat",U37,X37) | F37: =D37+E37 | H37: 30 | I37: =IF(I36="","",DATE(YEAR(I36),MONTH(I36)+1,DAY(I36))) | J37: =J36-K36 | K37: =IF('Usulan Pembiayaan'!$M$55="Flat",W37,T37) | L37: =IF('Usulan Pembiayaan'!$M$55="Flat",X37,U37) | M37: =K37+L37+67 | P37: =IF(Q32="Flat",Q33,IF(Q32="Efektif",Q28)) | Q37: =IF(Q32="Efektif",Q33,IF(Q32="Flat",Q28)) | T37: =IF(A37<=$R$4,$P$2/$R$4,0) | U37: =IF(A37<=$R$4,$U$8,0) | V37: =IF(A37<=$R$4,V36-W36,0) | W37: =Y37-X37 | X37: =IF(A37<=$R$4,V37*$R$6/12,0) | Y37: =IF(A37<=$R$4,$Y$8,0)
A38: 31 | B38: =IF(B37="","",DATE(YEAR(B37),MONTH(B37)+1,DAY(B37))) | C38: =C37-D37 | D38: =IF('Usulan Pembiayaan'!$M$55="Flat",T38,W38)+67 | E38: =IF('Usulan Pembiayaan'!$M$55="Flat",U38,X38) | F38: =D38+E38 | H38: 31 | I38: =IF(I37="","",DATE(YEAR(I37),MONTH(I37)+1,DAY(I37))) | J38: =J37-K37 | K38: =IF('Usulan Pembiayaan'!$M$55="Flat",W38,T38) | L38: =IF('Usulan Pembiayaan'!$M$55="Flat",X38,U38) | M38: =K38+L38+67 | P38: =P37*12 | Q38: =Q37*12 | T38: =IF(A38<=$R$4,$P$2/$R$4,0) | U38: =IF(A38<=$R$4,$U$8,0) | V38: =IF(A38<=$R$4,V37-W37,0) | W38: =Y38-X38 | X38: =IF(A38<=$R$4,V38*$R$6/12,0) | Y38: =IF(A38<=$R$4,$Y$8,0)
A39: 32 | B39: =IF(B38="","",DATE(YEAR(B38),MONTH(B38)+1,DAY(B38))) | C39: =C38-D38 | D39: =IF('Usulan Pembiayaan'!$M$55="Flat",T39,W39)+67 | E39: =IF('Usulan Pembiayaan'!$M$55="Flat",U39,X39) | F39: =D39+E39 | H39: 32 | I39: =IF(I38="","",DATE(YEAR(I38),MONTH(I38)+1,DAY(I38))) | J39: =J38-K38 | K39: =IF('Usulan Pembiayaan'!$M$55="Flat",W39,T39) | L39: =IF('Usulan Pembiayaan'!$M$55="Flat",X39,U39) | M39: =K39+L39+67 | T39: =IF(A39<=$R$4,$P$2/$R$4,0) | U39: =IF(A39<=$R$4,$U$8,0) | V39: =IF(A39<=$R$4,V38-W38,0) | W39: =Y39-X39 | X39: =IF(A39<=$R$4,V39*$R$6/12,0) | Y39: =IF(A39<=$R$4,$Y$8,0)
A40: 33 | B40: =IF(B39="","",DATE(YEAR(B39),MONTH(B39)+1,DAY(B39))) | C40: =C39-D39 | D40: =IF('Usulan Pembiayaan'!$M$55="Flat",T40,W40)+67 | E40: =IF('Usulan Pembiayaan'!$M$55="Flat",U40,X40) | F40: =D40+E40 | H40: 33 | I40: =IF(I39="","",DATE(YEAR(I39),MONTH(I39)+1,DAY(I39))) | J40: =J39-K39 | K40: =IF('Usulan Pembiayaan'!$M$55="Flat",W40,T40) | L40: =IF('Usulan Pembiayaan'!$M$55="Flat",X40,U40) | M40: =K40+L40+67 | T40: =IF(A40<=$R$4,$P$2/$R$4,0) | U40: =IF(A40<=$R$4,$U$8,0) | V40: =IF(A40<=$R$4,V39-W39,0) | W40: =Y40-X40 | X40: =IF(A40<=$R$4,V40*$R$6/12,0) | Y40: =IF(A40<=$R$4,$Y$8,0)
A41: 34 | B41: =IF(B40="","",DATE(YEAR(B40),MONTH(B40)+1,DAY(B40))) | C41: =C40-D40 | D41: =IF('Usulan Pembiayaan'!$M$55="Flat",T41,W41)+67 | E41: =IF('Usulan Pembiayaan'!$M$55="Flat",U41,X41) | F41: =D41+E41 | H41: 34 | I41: =IF(I40="","",DATE(YEAR(I40),MONTH(I40)+1,DAY(I40))) | J41: =J40-K40 | K41: =IF('Usulan Pembiayaan'!$M$55="Flat",W41,T41) | L41: =IF('Usulan Pembiayaan'!$M$55="Flat",X41,U41) | M41: =K41+L41+67 | T41: =IF(A41<=$R$4,$P$2/$R$4,0) | U41: =IF(A41<=$R$4,$U$8,0) | V41: =IF(A41<=$R$4,V40-W40,0) | W41: =Y41-X41 | X41: =IF(A41<=$R$4,V41*$R$6/12,0) | Y41: =IF(A41<=$R$4,$Y$8,0)
A42: 35 | B42: =IF(B41="","",DATE(YEAR(B41),MONTH(B41)+1,DAY(B41))) | C42: =C41-D41 | D42: =IF('Usulan Pembiayaan'!$M$55="Flat",T42,W42)+67 | E42: =IF('Usulan Pembiayaan'!$M$55="Flat",U42,X42) | F42: =D42+E42 | H42: 35 | I42: =IF(I41="","",DATE(YEAR(I41),MONTH(I41)+1,DAY(I41))) | J42: =J41-K41 | K42: =IF('Usulan Pembiayaan'!$M$55="Flat",W42,T42) | L42: =IF('Usulan Pembiayaan'!$M$55="Flat",X42,U42) | M42: =K42+L42+67 | T42: =IF(A42<=$R$4,$P$2/$R$4,0) | U42: =IF(A42<=$R$4,$U$8,0) | V42: =IF(A42<=$R$4,V41-W41,0) | W42: =Y42-X42 | X42: =IF(A42<=$R$4,V42*$R$6/12,0) | Y42: =IF(A42<=$R$4,$Y$8,0)
A43: 36 | B43: =IF(B42="","",DATE(YEAR(B42),MONTH(B42)+1,DAY(B42))) | C43: =C42-D42 | D43: =IF('Usulan Pembiayaan'!$M$55="Flat",T43,W43)+67 | E43: =IF('Usulan Pembiayaan'!$M$55="Flat",U43,X43) | F43: =D43+E43 | H43: 36 | I43: =IF(I42="","",DATE(YEAR(I42),MONTH(I42)+1,DAY(I42))) | J43: =J42-K42 | K43: =IF('Usulan Pembiayaan'!$M$55="Flat",W43,T43) | L43: =IF('Usulan Pembiayaan'!$M$55="Flat",X43,U43) | M43: =K43+L43+67 | Q43: =P43-F43 | T43: =IF(A43<=$R$4,$P$2/$R$4,0) | U43: =IF(A43<=$R$4,$U$8,0) | V43: =IF(A43<=$R$4,V42-W42,0) | W43: =Y43-X43 | X43: =IF(A43<=$R$4,V43*$R$6/12,0) | Y43: =IF(A43<=$R$4,$Y$8,0)
A44: 37 | B44: =IF(B43="","",DATE(YEAR(B43),MONTH(B43)+1,DAY(B43))) | C44: =C43-D43 | D44: =IF('Usulan Pembiayaan'!$M$55="Flat",T44,W44)+67 | E44: =IF('Usulan Pembiayaan'!$M$55="Flat",U44,X44) | F44: =D44+E44 | H44: 37 | I44: =IF(I43="","",DATE(YEAR(I43),MONTH(I43)+1,DAY(I43))) | J44: =J43-K43 | K44: =IF('Usulan Pembiayaan'!$M$55="Flat",W44,T44) | L44: =IF('Usulan Pembiayaan'!$M$55="Flat",X44,U44) | M44: =K44+L44+67 | T44: =IF(A44<=$R$4,$P$2/$R$4,0) | U44: =IF(A44<=$R$4,$U$8,0) | V44: =IF(A44<=$R$4,V43-W43,0) | W44: =Y44-X44 | X44: =IF(A44<=$R$4,V44*$R$6/12,0) | Y44: =IF(A44<=$R$4,$Y$8,0)
A45: 38 | B45: =IF(B44="","",DATE(YEAR(B44),MONTH(B44)+1,DAY(B44))) | C45: =C44-D44 | D45: =IF('Usulan Pembiayaan'!$M$55="Flat",T45,W45)+67 | E45: =IF('Usulan Pembiayaan'!$M$55="Flat",U45,X45) | F45: =D45+E45 | H45: 38 | I45: =IF(I44="","",DATE(YEAR(I44),MONTH(I44)+1,DAY(I44))) | J45: =J44-K44 | K45: =IF('Usulan Pembiayaan'!$M$55="Flat",W45,T45) | L45: =IF('Usulan Pembiayaan'!$M$55="Flat",X45,U45) | M45: =K45+L45+67 | T45: =IF(A45<=$R$4,$P$2/$R$4,0) | U45: =IF(A45<=$R$4,$U$8,0) | V45: =IF(A45<=$R$4,V44-W44,0) | W45: =Y45-X45 | X45: =IF(A45<=$R$4,V45*$R$6/12,0) | Y45: =IF(A45<=$R$4,$Y$8,0)
A46: 39 | B46: =IF(B45="","",DATE(YEAR(B45),MONTH(B45)+1,DAY(B45))) | C46: =C45-D45 | D46: =IF('Usulan Pembiayaan'!$M$55="Flat",T46,W46)+67 | E46: =IF('Usulan Pembiayaan'!$M$55="Flat",U46,X46) | F46: =D46+E46 | H46: 39 | I46: =IF(I45="","",DATE(YEAR(I45),MONTH(I45)+1,DAY(I45))) | J46: =J45-K45 | K46: =IF('Usulan Pembiayaan'!$M$55="Flat",W46,T46) | L46: =IF('Usulan Pembiayaan'!$M$55="Flat",X46,U46) | M46: =K46+L46+67 | T46: =IF(A46<=$R$4,$P$2/$R$4,0) | U46: =IF(A46<=$R$4,$U$8,0) | V46: =IF(A46<=$R$4,V45-W45,0) | W46: =Y46-X46 | X46: =IF(A46<=$R$4,V46*$R$6/12,0) | Y46: =IF(A46<=$R$4,$Y$8,0)
A47: 40 | B47: =IF(B46="","",DATE(YEAR(B46),MONTH(B46)+1,DAY(B46))) | C47: =C46-D46 | D47: =IF('Usulan Pembiayaan'!$M$55="Flat",T47,W47)+67 | E47: =IF('Usulan Pembiayaan'!$M$55="Flat",U47,X47) | F47: =D47+E47 | H47: 40 | I47: =IF(I46="","",DATE(YEAR(I46),MONTH(I46)+1,DAY(I46))) | J47: =J46-K46 | K47: =IF('Usulan Pembiayaan'!$M$55="Flat",W47,T47) | L47: =IF('Usulan Pembiayaan'!$M$55="Flat",X47,U47) | M47: =K47+L47+67 | T47: =IF(A47<=$R$4,$P$2/$R$4,0) | U47: =IF(A47<=$R$4,$U$8,0) | V47: =IF(A47<=$R$4,V46-W46,0) | W47: =Y47-X47 | X47: =IF(A47<=$R$4,V47*$R$6/12,0) | Y47: =IF(A47<=$R$4,$Y$8,0)
A48: 41 | B48: =IF(B47="","",DATE(YEAR(B47),MONTH(B47)+1,DAY(B47))) | C48: =C47-D47 | D48: =IF('Usulan Pembiayaan'!$M$55="Flat",T48,W48)+67 | E48: =IF('Usulan Pembiayaan'!$M$55="Flat",U48,X48) | F48: =D48+E48 | H48: 41 | I48: =IF(I47="","",DATE(YEAR(I47),MONTH(I47)+1,DAY(I47))) | J48: =J47-K47 | K48: =IF('Usulan Pembiayaan'!$M$55="Flat",W48,T48) | L48: =IF('Usulan Pembiayaan'!$M$55="Flat",X48,U48) | M48: =K48+L48+67 | T48: =IF(A48<=$R$4,$P$2/$R$4,0) | U48: =IF(A48<=$R$4,$U$8,0) | V48: =IF(A48<=$R$4,V47-W47,0) | W48: =Y48-X48 | X48: =IF(A48<=$R$4,V48*$R$6/12,0) | Y48: =IF(A48<=$R$4,$Y$8,0)
A49: 42 | B49: =IF(B48="","",DATE(YEAR(B48),MONTH(B48)+1,DAY(B48))) | C49: =C48-D48 | D49: =IF('Usulan Pembiayaan'!$M$55="Flat",T49,W49)+67 | E49: =IF('Usulan Pembiayaan'!$M$55="Flat",U49,X49) | F49: =D49+E49 | H49: 42 | I49: =IF(I48="","",DATE(YEAR(I48),MONTH(I48)+1,DAY(I48))) | J49: =J48-K48 | K49: =IF('Usulan Pembiayaan'!$M$55="Flat",W49,T49) | L49: =IF('Usulan Pembiayaan'!$M$55="Flat",X49,U49) | M49: =K49+L49+67 | T49: =IF(A49<=$R$4,$P$2/$R$4,0) | U49: =IF(A49<=$R$4,$U$8,0) | V49: =IF(A49<=$R$4,V48-W48,0) | W49: =Y49-X49 | X49: =IF(A49<=$R$4,V49*$R$6/12,0) | Y49: =IF(A49<=$R$4,$Y$8,0)
A50: 43 | B50: =IF(B49="","",DATE(YEAR(B49),MONTH(B49)+1,DAY(B49))) | C50: =C49-D49 | D50: =IF('Usulan Pembiayaan'!$M$55="Flat",T50,W50)+67 | E50: =IF('Usulan Pembiayaan'!$M$55="Flat",U50,X50) | F50: =D50+E50 | H50: 43 | I50: =IF(I49="","",DATE(YEAR(I49),MONTH(I49)+1,DAY(I49))) | J50: =J49-K49 | K50: =IF('Usulan Pembiayaan'!$M$55="Flat",W50,T50) | L50: =IF('Usulan Pembiayaan'!$M$55="Flat",X50,U50) | M50: =K50+L50+67 | T50: =IF(A50<=$R$4,$P$2/$R$4,0) | U50: =IF(A50<=$R$4,$U$8,0) | V50: =IF(A50<=$R$4,V49-W49,0) | W50: =Y50-X50 | X50: =IF(A50<=$R$4,V50*$R$6/12,0) | Y50: =IF(A50<=$R$4,$Y$8,0)
A51: 44 | B51: =IF(B50="","",DATE(YEAR(B50),MONTH(B50)+1,DAY(B50))) | C51: =C50-D50 | D51: =IF('Usulan Pembiayaan'!$M$55="Flat",T51,W51)+67 | E51: =IF('Usulan Pembiayaan'!$M$55="Flat",U51,X51) | F51: =D51+E51 | H51: 44 | I51: =IF(I50="","",DATE(YEAR(I50),MONTH(I50)+1,DAY(I50))) | J51: =J50-K50 | K51: =IF('Usulan Pembiayaan'!$M$55="Flat",W51,T51) | L51: =IF('Usulan Pembiayaan'!$M$55="Flat",X51,U51) | M51: =K51+L51+67 | T51: =IF(A51<=$R$4,$P$2/$R$4,0) | U51: =IF(A51<=$R$4,$U$8,0) | V51: =IF(A51<=$R$4,V50-W50,0) | W51: =Y51-X51 | X51: =IF(A51<=$R$4,V51*$R$6/12,0) | Y51: =IF(A51<=$R$4,$Y$8,0)
A52: 45 | B52: =IF(B51="","",DATE(YEAR(B51),MONTH(B51)+1,DAY(B51))) | C52: =C51-D51 | D52: =IF('Usulan Pembiayaan'!$M$55="Flat",T52,W52)+67 | E52: =IF('Usulan Pembiayaan'!$M$55="Flat",U52,X52) | F52: =D52+E52 | H52: 45 | I52: =IF(I51="","",DATE(YEAR(I51),MONTH(I51)+1,DAY(I51))) | J52: =J51-K51 | K52: =IF('Usulan Pembiayaan'!$M$55="Flat",W52,T52) | L52: =IF('Usulan Pembiayaan'!$M$55="Flat",X52,U52) | M52: =K52+L52+67 | T52: =IF(A52<=$R$4,$P$2/$R$4,0) | U52: =IF(A52<=$R$4,$U$8,0) | V52: =IF(A52<=$R$4,V51-W51,0) | W52: =Y52-X52 | X52: =IF(A52<=$R$4,V52*$R$6/12,0) | Y52: =IF(A52<=$R$4,$Y$8,0)
A53: 46 | B53: =IF(B52="","",DATE(YEAR(B52),MONTH(B52)+1,DAY(B52))) | C53: =C52-D52 | D53: =IF('Usulan Pembiayaan'!$M$55="Flat",T53,W53)+67 | E53: =IF('Usulan Pembiayaan'!$M$55="Flat",U53,X53) | F53: =D53+E53 | H53: 46 | I53: =IF(I52="","",DATE(YEAR(I52),MONTH(I52)+1,DAY(I52))) | J53: =J52-K52 | K53: =IF('Usulan Pembiayaan'!$M$55="Flat",W53,T53) | L53: =IF('Usulan Pembiayaan'!$M$55="Flat",X53,U53) | M53: =K53+L53+67 | T53: =IF(A53<=$R$4,$P$2/$R$4,0) | U53: =IF(A53<=$R$4,$U$8,0) | V53: =IF(A53<=$R$4,V52-W52,0) | W53: =Y53-X53 | X53: =IF(A53<=$R$4,V53*$R$6/12,0) | Y53: =IF(A53<=$R$4,$Y$8,0)
A54: 47 | B54: =IF(B53="","",DATE(YEAR(B53),MONTH(B53)+1,DAY(B53))) | C54: =C53-D53 | D54: =IF('Usulan Pembiayaan'!$M$55="Flat",T54,W54)+67 | E54: =IF('Usulan Pembiayaan'!$M$55="Flat",U54,X54) | F54: =D54+E54 | H54: 47 | I54: =IF(I53="","",DATE(YEAR(I53),MONTH(I53)+1,DAY(I53))) | J54: =J53-K53 | K54: =IF('Usulan Pembiayaan'!$M$55="Flat",W54,T54) | L54: =IF('Usulan Pembiayaan'!$M$55="Flat",X54,U54) | M54: =K54+L54+67 | T54: =IF(A54<=$R$4,$P$2/$R$4,0) | U54: =IF(A54<=$R$4,$U$8,0) | V54: =IF(A54<=$R$4,V53-W53,0) | W54: =Y54-X54 | X54: =IF(A54<=$R$4,V54*$R$6/12,0) | Y54: =IF(A54<=$R$4,$Y$8,0)
A55: 48 | B55: =IF(B54="","",DATE(YEAR(B54),MONTH(B54)+1,DAY(B54))) | C55: =C54-D54 | D55: =IF('Usulan Pembiayaan'!$M$55="Flat",T55,W55)+67 | E55: =IF('Usulan Pembiayaan'!$M$55="Flat",U55,X55) | F55: =D55+E55 | H55: 48 | I55: =IF(I54="","",DATE(YEAR(I54),MONTH(I54)+1,DAY(I54))) | J55: =J54-K54 | K55: =IF('Usulan Pembiayaan'!$M$55="Flat",W55,T55) | L55: =IF('Usulan Pembiayaan'!$M$55="Flat",X55,U55) | M55: =K55+L55+67 | T55: =IF(A55<=$R$4,$P$2/$R$4,0) | U55: =IF(A55<=$R$4,$U$8,0) | V55: =IF(A55<=$R$4,V54-W54,0) | W55: =Y55-X55 | X55: =IF(A55<=$R$4,V55*$R$6/12,0) | Y55: =IF(A55<=$R$4,$Y$8,0)
A56: 49 | B56: =IF(B55="","",DATE(YEAR(B55),MONTH(B55)+1,DAY(B55))) | C56: =C55-D55 | D56: =IF('Usulan Pembiayaan'!$M$55="Flat",T56,W56) | E56: =IF('Usulan Pembiayaan'!$M$55="Flat",U56,X56) | F56: =D56+E56 | H56: 49 | I56: =IF(I55="","",DATE(YEAR(I55),MONTH(I55)+1,DAY(I55))) | J56: =J55-K55 | K56: =IF('Usulan Pembiayaan'!$M$55="Flat",W56,T56) | L56: =IF('Usulan Pembiayaan'!$M$55="Flat",X56,U56) | M56: =K56+L56 | T56: =IF(A56<=$R$4,$P$2/$R$4,0) | U56: =IF(A56<=$R$4,$U$8,0) | V56: =IF(A56<=$R$4,V55-W55,0) | W56: =Y56-X56 | X56: =IF(A56<=$R$4,V56*$R$6/12,0) | Y56: =IF(A56<=$R$4,$Y$8,0)
A57: 50 | B57: =IF(B56="","",DATE(YEAR(B56),MONTH(B56)+1,DAY(B56))) | C57: =C56-D56 | D57: =IF('Usulan Pembiayaan'!$M$55="Flat",T57,W57) | E57: =IF('Usulan Pembiayaan'!$M$55="Flat",U57,X57) | F57: =D57+E57 | H57: 50 | I57: =IF(I56="","",DATE(YEAR(I56),MONTH(I56)+1,DAY(I56))) | J57: =J56-K56 | K57: =IF('Usulan Pembiayaan'!$M$55="Flat",W57,T57) | L57: =IF('Usulan Pembiayaan'!$M$55="Flat",X57,U57) | M57: =K57+L57 | T57: =IF(A57<=$R$4,$P$2/$R$4,0) | U57: =IF(A57<=$R$4,$U$8,0) | V57: =IF(A57<=$R$4,V56-W56,0) | W57: =Y57-X57 | X57: =IF(A57<=$R$4,V57*$R$6/12,0) | Y57: =IF(A57<=$R$4,$Y$8,0)
A58: 51 | B58: =IF(B57="","",DATE(YEAR(B57),MONTH(B57)+1,DAY(B57))) | C58: =C57-D57 | D58: =IF('Usulan Pembiayaan'!$M$55="Flat",T58,W58) | E58: =IF('Usulan Pembiayaan'!$M$55="Flat",U58,X58) | F58: 0 | H58: 51 | I58: =IF(I57="","",DATE(YEAR(I57),MONTH(I57)+1,DAY(I57))) | J58: =J57-K57 | K58: =IF('Usulan Pembiayaan'!$M$55="Flat",W58,T58) | L58: =IF('Usulan Pembiayaan'!$M$55="Flat",X58,U58) | M58: =K58+L58 | T58: =IF(A58<=$R$4,$P$2/$R$4,0) | U58: =IF(A58<=$R$4,$U$8,0) | V58: =IF(A58<=$R$4,V57-W57,0) | W58: =Y58-X58 | X58: =IF(A58<=$R$4,V58*$R$6/12,0) | Y58: =IF(A58<=$R$4,$Y$8,0)
A59: 52 | B59: =IF(B58="","",DATE(YEAR(B58),MONTH(B58)+1,DAY(B58))) | C59: =C58-D58 | D59: =IF('Usulan Pembiayaan'!$M$55="Flat",T59,W59) | E59: =IF('Usulan Pembiayaan'!$M$55="Flat",U59,X59) | F59: =D59+E59 | H59: 52 | I59: =IF(I58="","",DATE(YEAR(I58),MONTH(I58)+1,DAY(I58))) | J59: =J58-K58 | K59: =IF('Usulan Pembiayaan'!$M$55="Flat",W59,T59) | L59: =IF('Usulan Pembiayaan'!$M$55="Flat",X59,U59) | M59: =K59+L59 | T59: =IF(A59<=$R$4,$P$2/$R$4,0) | U59: =IF(A59<=$R$4,$U$8,0) | V59: =IF(A59<=$R$4,V58-W58,0) | W59: =Y59-X59 | X59: =IF(A59<=$R$4,V59*$R$6/12,0) | Y59: =IF(A59<=$R$4,$Y$8,0)
A60: 53 | B60: =IF(B59="","",DATE(YEAR(B59),MONTH(B59)+1,DAY(B59))) | C60: =C59-D59 | D60: =IF('Usulan Pembiayaan'!$M$55="Flat",T60,W60) | E60: =IF('Usulan Pembiayaan'!$M$55="Flat",U60,X60) | F60: =D60+E60 | H60: 53 | I60: =IF(I59="","",DATE(YEAR(I59),MONTH(I59)+1,DAY(I59))) | J60: =J59-K59 | K60: =IF('Usulan Pembiayaan'!$M$55="Flat",W60,T60) | L60: =IF('Usulan Pembiayaan'!$M$55="Flat",X60,U60) | M60: =K60+L60 | T60: =IF(A60<=$R$4,$P$2/$R$4,0) | U60: =IF(A60<=$R$4,$U$8,0) | V60: =IF(A60<=$R$4,V59-W59,0) | W60: =Y60-X60 | X60: =IF(A60<=$R$4,V60*$R$6/12,0) | Y60: =IF(A60<=$R$4,$Y$8,0)
A61: 54 | B61: =IF(B60="","",DATE(YEAR(B60),MONTH(B60)+1,DAY(B60))) | C61: =C60-D60 | D61: =IF('Usulan Pembiayaan'!$M$55="Flat",T61,W61) | E61: =IF('Usulan Pembiayaan'!$M$55="Flat",U61,X61) | F61: =D61+E61 | H61: 54 | I61: =IF(I60="","",DATE(YEAR(I60),MONTH(I60)+1,DAY(I60))) | J61: =J60-K60 | K61: =IF('Usulan Pembiayaan'!$M$55="Flat",W61,T61) | L61: =IF('Usulan Pembiayaan'!$M$55="Flat",X61,U61) | M61: =K61+L61 | T61: =IF(A61<=$R$4,$P$2/$R$4,0) | U61: =IF(A61<=$R$4,$U$8,0) | V61: =IF(A61<=$R$4,V60-W60,0) | W61: =Y61-X61 | X61: =IF(A61<=$R$4,V61*$R$6/12,0) | Y61: =IF(A61<=$R$4,$Y$8,0)
A62: 55 | B62: =IF(B61="","",DATE(YEAR(B61),MONTH(B61)+1,DAY(B61))) | C62: =C61-D61 | D62: =IF('Usulan Pembiayaan'!$M$55="Flat",T62,W62) | E62: =IF('Usulan Pembiayaan'!$M$55="Flat",U62,X62) | F62: =D62+E62 | H62: 55 | I62: =IF(I61="","",DATE(YEAR(I61),MONTH(I61)+1,DAY(I61))) | J62: =J61-K61 | K62: =IF('Usulan Pembiayaan'!$M$55="Flat",W62,T62) | L62: =IF('Usulan Pembiayaan'!$M$55="Flat",X62,U62) | M62: =K62+L62 | T62: =IF(A62<=$R$4,$P$2/$R$4,0) | U62: =IF(A62<=$R$4,$U$8,0) | V62: =IF(A62<=$R$4,V61-W61,0) | W62: =Y62-X62 | X62: =IF(A62<=$R$4,V62*$R$6/12,0) | Y62: =IF(A62<=$R$4,$Y$8,0)
A63: 56 | B63: =IF(B62="","",DATE(YEAR(B62),MONTH(B62)+1,DAY(B62))) | C63: =C62-D62 | D63: =IF('Usulan Pembiayaan'!$M$55="Flat",T63,W63) | E63: =IF('Usulan Pembiayaan'!$M$55="Flat",U63,X63) | F63: =D63+E63 | H63: 56 | I63: =IF(I62="","",DATE(YEAR(I62),MONTH(I62)+1,DAY(I62))) | J63: =J62-K62 | K63: =IF('Usulan Pembiayaan'!$M$55="Flat",W63,T63) | L63: =IF('Usulan Pembiayaan'!$M$55="Flat",X63,U63) | M63: =K63+L63 | T63: =IF(A63<=$R$4,$P$2/$R$4,0) | U63: =IF(A63<=$R$4,$U$8,0) | V63: =IF(A63<=$R$4,V62-W62,0) | W63: =Y63-X63 | X63: =IF(A63<=$R$4,V63*$R$6/12,0) | Y63: =IF(A63<=$R$4,$Y$8,0)
A64: 57 | B64: =IF(B63="","",DATE(YEAR(B63),MONTH(B63)+1,DAY(B63))) | C64: =C63-D63 | D64: =IF('Usulan Pembiayaan'!$M$55="Flat",T64,W64) | E64: =IF('Usulan Pembiayaan'!$M$55="Flat",U64,X64) | F64: =D64+E64 | H64: 57 | I64: =IF(I63="","",DATE(YEAR(I63),MONTH(I63)+1,DAY(I63))) | J64: =J63-K63 | K64: =IF('Usulan Pembiayaan'!$M$55="Flat",W64,T64) | L64: =IF('Usulan Pembiayaan'!$M$55="Flat",X64,U64) | M64: =K64+L64 | T64: =IF(A64<=$R$4,$P$2/$R$4,0) | U64: =IF(A64<=$R$4,$U$8,0) | V64: =IF(A64<=$R$4,V63-W63,0) | W64: =Y64-X64 | X64: =IF(A64<=$R$4,V64*$R$6/12,0) | Y64: =IF(A64<=$R$4,$Y$8,0)
A65: 58 | B65: =IF(B64="","",DATE(YEAR(B64),MONTH(B64)+1,DAY(B64))) | C65: =C64-D64 | D65: =IF('Usulan Pembiayaan'!$M$55="Flat",T65,W65) | E65: =IF('Usulan Pembiayaan'!$M$55="Flat",U65,X65) | F65: =D65+E65 | H65: 58 | I65: =IF(I64="","",DATE(YEAR(I64),MONTH(I64)+1,DAY(I64))) | J65: =J64-K64 | K65: =IF('Usulan Pembiayaan'!$M$55="Flat",W65,T65) | L65: =IF('Usulan Pembiayaan'!$M$55="Flat",X65,U65) | M65: =K65+L65 | T65: =IF(A65<=$R$4,$P$2/$R$4,0) | U65: =IF(A65<=$R$4,$U$8,0) | V65: =IF(A65<=$R$4,V64-W64,0) | W65: =Y65-X65 | X65: =IF(A65<=$R$4,V65*$R$6/12,0) | Y65: =IF(A65<=$R$4,$Y$8,0)
A66: 59 | B66: =IF(B65="","",DATE(YEAR(B65),MONTH(B65)+1,DAY(B65))) | C66: =C65-D65 | D66: =IF('Usulan Pembiayaan'!$M$55="Flat",T66,W66) | E66: =IF('Usulan Pembiayaan'!$M$55="Flat",U66,X66) | F66: =D66+E66 | H66: 59 | I66: =IF(I65="","",DATE(YEAR(I65),MONTH(I65)+1,DAY(I65))) | J66: =J65-K65 | K66: =IF('Usulan Pembiayaan'!$M$55="Flat",W66,T66) | L66: =IF('Usulan Pembiayaan'!$M$55="Flat",X66,U66) | M66: =K66+L66 | T66: =IF(A66<=$R$4,$P$2/$R$4,0) | U66: =IF(A66<=$R$4,$U$8,0) | V66: =IF(A66<=$R$4,V65-W65,0) | W66: =Y66-X66 | X66: =IF(A66<=$R$4,V66*$R$6/12,0) | Y66: =IF(A66<=$R$4,$Y$8,0)
A67: 60 | B67: =IF(B66="","",DATE(YEAR(B66),MONTH(B66)+1,DAY(B66))) | C67: =C66-D66 | D67: =IF('Usulan Pembiayaan'!$M$55="Flat",T67,W67) | E67: =IF('Usulan Pembiayaan'!$M$55="Flat",U67,X67) | F67: =D67+E67 | H67: 60 | I67: =IF(I66="","",DATE(YEAR(I66),MONTH(I66)+1,DAY(I66))) | J67: =J66-K66 | K67: =IF('Usulan Pembiayaan'!$M$55="Flat",W67,T67) | L67: =IF('Usulan Pembiayaan'!$M$55="Flat",X67,U67) | M67: =K67+L67 | T67: =IF(A67<=$R$4,$P$2/$R$4,0) | U67: =IF(A67<=$R$4,$U$8,0) | V67: =IF(A67<=$R$4,V66-W66,0) | W67: =Y67-X67 | X67: =IF(A67<=$R$4,V67*$R$6/12,0) | Y67: =IF(A67<=$R$4,$Y$8,0)
A68: 61 | B68: =IF(B67="","",DATE(YEAR(B67),MONTH(B67)+1,DAY(B67))) | C68: =C67-D67 | D68: =IF('Usulan Pembiayaan'!$M$55="Flat",T68,W68) | E68: =IF('Usulan Pembiayaan'!$M$55="Flat",U68,X68) | F68: =D68+E68 | H68: 61 | I68: =IF(I67="","",DATE(YEAR(I67),MONTH(I67)+1,DAY(I67))) | J68: =J67-K67 | K68: =IF('Usulan Pembiayaan'!$M$55="Flat",W68,T68) | L68: =IF('Usulan Pembiayaan'!$M$55="Flat",X68,U68) | M68: =K68+L68 | T68: =IF(A68<=$R$4,$P$2/$R$4,0) | U68: =IF(A68<=$R$4,$U$8,0) | V68: =IF(A68<=$R$4,V67-W67,0) | W68: =Y68-X68 | X68: =IF(A68<=$R$4,V68*$R$6/12,0) | Y68: =IF(A68<=$R$4,$Y$8,0)
A69: 62 | B69: =IF(B68="","",DATE(YEAR(B68),MONTH(B68)+1,DAY(B68))) | C69: =C68-D68 | D69: =IF('Usulan Pembiayaan'!$M$55="Flat",T69,W69) | E69: =IF('Usulan Pembiayaan'!$M$55="Flat",U69,X69) | F69: =D69+E69 | H69: 62 | I69: =IF(I68="","",DATE(YEAR(I68),MONTH(I68)+1,DAY(I68))) | J69: =J68-K68 | K69: =IF('Usulan Pembiayaan'!$M$55="Flat",W69,T69) | L69: =IF('Usulan Pembiayaan'!$M$55="Flat",X69,U69) | M69: =K69+L69 | T69: =IF(A69<=$R$4,$P$2/$R$4,0) | U69: =IF(A69<=$R$4,$U$8,0) | V69: =IF(A69<=$R$4,V68-W68,0) | W69: =Y69-X69 | X69: =IF(A69<=$R$4,V69*$R$6/12,0) | Y69: =IF(A69<=$R$4,$Y$8,0)
A70: 63 | B70: =IF(B69="","",DATE(YEAR(B69),MONTH(B69)+1,DAY(B69))) | C70: =C69-D69 | D70: =IF('Usulan Pembiayaan'!$M$55="Flat",T70,W70) | E70: =IF('Usulan Pembiayaan'!$M$55="Flat",U70,X70) | F70: =D70+E70 | H70: 63 | I70: =IF(I69="","",DATE(YEAR(I69),MONTH(I69)+1,DAY(I69))) | J70: =J69-K69 | K70: =IF('Usulan Pembiayaan'!$M$55="Flat",W70,T70) | L70: =IF('Usulan Pembiayaan'!$M$55="Flat",X70,U70) | M70: =K70+L70 | T70: =IF(A70<=$R$4,$P$2/$R$4,0) | U70: =IF(A70<=$R$4,$U$8,0) | V70: =IF(A70<=$R$4,V69-W69,0) | W70: =Y70-X70 | X70: =IF(A70<=$R$4,V70*$R$6/12,0) | Y70: =IF(A70<=$R$4,$Y$8,0)
... A127: 120 | B127: =IF(B126="","",DATE(YEAR(B126),MONTH(B126)+1,DAY(B126))) | C127: =C126-D126 | D127: =IF('Usulan Pembiayaan'!$M$55="Flat",T127,W127) | E127: =IF('Usulan Pembiayaan'!$M$55="Flat",U127,X127) | F127: =D127+E127 | H127: 120 | I127: =IF(I126="","",DATE(YEAR(I126),MONTH(I126)+1,DAY(I126))) | J127: =J126-K126 | K127: =IF('Usulan Pembiayaan'!$M$55="Flat",W127,T127) | L127: =IF('Usulan Pembiayaan'!$M$55="Flat",X127,U127) | M127: =K127+L127 | T127: =IF(A127<=$R$4,$P$2/$R$4,0) | U127: =IF(A127<=$R$4,$U$8,0) | V127: =IF(A127<=$R$4,V126-W126,0) | W127: =Y127-X127 | X127: =IF(A127<=$R$4,V127*$R$6/12,0) | Y127: =IF(A127<=$R$4,$Y$8,0)
T128: 0 | U128: 0 | V128: 0 | W128: 0 | X128: 0
A129: Total | D129: =SUM(D8:D128) | E129: =SUM(E8:E128) | F129: =SUM(F8:F55) | H129: Total | K129: =SUM(K8:K128) | L129: =SUM(L8:L128) | M129: =SUM(M8:M128) | T129: =SUM(T8:T128) | U129: =SUM(U8:U128) | W129: =SUM(W8:W128) | X129: =SUM(X8:X128) | Y129: =SUM(Y8:Y128)
A131: ="Bogor, "&TEXT(TODAY(),("dd mmmm yyyy")) | H131: ="Bogor, "&TEXT(TODAY(),("dd mmmm yyyy")) | X131: =X129-U129
A133: Nasabah, | E133: Suami/Istri | H133: Nasabah, | L133: Suami/Istri
A139: ='Keputusan Pembiayaan'!N11 | E139: ______________________ | H139: ='[6]Keputusan Pembiayaan'!T11 | L139: ______________________

Sheet Parameter
A1: PARAMETER KREDIT SCORING KCR | H1: EXISTING | L1: <=50juta
H2: BBT (a) | I2: % Fktr (b) | J2: % Var © | K2: Nilai = a x b x c | L2: BBT (a) | M2: % Fktr (b) | N2: % Var © | O2: Nilai = a x b x c
A4: STEP 1 - INFORMASI DASAR
A5: (a) | B5: Usia Calon Nasabah | U5: Tering
D6: 1 | E6: =IF($G$32<=2,J254,K254) | H6: 100 | I6: 0.15 | J6: 0.25 | K6: =H6*I6*J6 | L6: 50 | M6: 0.05 | N6: 0.3 | O6: =L6*M6*N6
D7: 2 | E7: =IF($G$32<=2,J255,K255) | H7: 80 | I7: 0.15 | J7: 0.25 | K7: =H7*I7*J7 | L7: 85 | M7: 0.05 | N7: 0.3 | O7: =L7*M7*N7 | U7: =VLOOKUP('Informasi Pokok'!I14,Parameter!E6:K9,7,0)
D8: 3 | E8: =IF($G$32<=2,J256,K256) | H8: 60 | I8: 0.15 | J8: 0.25 | K8: =H8*I8*J8 | L8: 100 | M8: 0.05 | N8: 0.3 | O8: =L8*M8*N8
D9: 4 | E9: =IF($G$32<=2,J257,K257) | H9: 40 | I9: 0.15 | J9: 0.25 | K9: =H9*I9*J9 | L9: 70 | M9: 0.05 | N9: 0.3 | O9: =L9*M9*N9 | P9: =K6 | Q9: =K7 | R9: =K8 | S9: =K9
A10: (b) | B10: Status Perkawinan
D11: 1 | E11: Menikah | H11: 100 | I11: 0.15 | J11: 0.2 | K11: =H11*I11*J11 | L11: 80 | M11: 0.05 | N11: 0.25 | O11: =L11*M11*N11
D12: 2 | E12: Lajang | H12: 80 | I12: 0.15 | J12: 0.2 | K12: =H12*I12*J12 | L12: 100 | M12: 0.05 | N12: 0.25 | O12: =L12*M12*N12 | P12: =K11 | Q12: =K12 | S12: =K13 | T12: lajang | U12: =VLOOKUP('Informasi Pokok'!D21,Parameter!E11:K13,7,0)
D13: 3 | E13: Cerai | H13: 65 | I13: 0.15 | J13: 0.2 | K13: =H13*I13*J13
A14: (c) | B14: Jumlah Tanggungan
D15: 1 | E15: > 5 Orang | H15: 25 | I15: 0.1 | J15: 0.3 | K15: =H15*I15*J15 | L15: 25 | M15: 0.05 | N15: 0.45 | O15: =L15*M15*N15
D16: 2 | E16: 3 - 5 Orang | H16: 50 | I16: 0.1 | J16: 0.3 | K16: =H16*I16*J16 | L16: 50 | M16: 0.05 | N16: 0.45 | O16: =L16*M16*N16
D17: 3 | E17: 1 - 2 Orang | H17: 75 | I17: 0.1 | J17: 0.3 | K17: =H17*I17*J17 | L17: 75 | M17: 0.05 | N17: 0.45 | O17: =L17*M17*N17
D18: 4 | E18: Tidak Mempunyai Tanggungan | H18: 100 | I18: 0.1 | J18: 0.3 | K18: =H18*I18*J18 | L18: 100 | M18: 0.05 | N18: 0.45 | O18: =L18*M18*N18 | P18: =K18 | Q18: =K17 | R18: =K16 | S18: =K15 | U18: =VLOOKUP('Informasi Pokok'!$D$22,Parameter!$E$15:$K$18,7,0)
A19: (d) | B19: Tingkat Pendidikan
D20: 1 | E20: SMA | H20: 25 | I20: 0.15 | J20: 0.2 | K20: =H20*I20*J20
D21: 2 | E21: D1 - D4 | H21: 50 | I21: 0.15 | J21: 0.2 | K21: =H21*I21*J21
D22: 3 | E22: S1 | H22: 75 | I22: 0.15 | J22: 0.2 | K22: =H22*I22*J22
D23: 4 | E23: S2 - S3 | H23: 100 | I23: 0.15 | J23: 0.2 | K23: =H23*I23*J23 | P23: =K23 | Q23: =K22 | R23: =K21 | S23: =K20 | U23: =VLOOKUP('Informasi Pokok'!$D$23,Parameter!E20:K23,7,0)
A26: (a) | B26: Kepemilikan tempat tinggal
D27: 1 | E27: Sewa | H27: 25 | I27: 0.25 | J27: 0.2 | K27: =H27*I27*J27 | L27: 25 | M27: 0.1 | N27: 0.6 | O27: =L27*M27*N27
D28: 2 | E28: Lain-lain (Menumpang) | H28: 50 | I28: 0.25 | J28: 0.2 | K28: =H28*I28*J28 | L28: 50 | M28: 0.1 | N28: 0.6 | O28: =L28*M28*N28
D29: 3 | E29: Angsuran | H29: 75 | I29: 0.25 | J29: 0.2 | K29: =H29*I29*J29 | L29: 75 | M29: 0.1 | N29: 0.6 | O29: =L29*M29*N29
D30: 4 | E30: Milik sendiri | H30: 100 | I30: 0.25 | J30: 0.2 | K30: =H30*I30*J30 | L30: 100 | M30: 0.1 | N30: 0.6 | O30: =L30*M30*N30 | P30: =K30 | Q30: =K29 | R30: =K28 | S30: =K27 | U30: =VLOOKUP('Informasi Pokok'!$D$24,Parameter!E27:K30,7,0)
A31: (b) | B31: Status Karyawan
D32: 1 | E32: TNI/POLRI | F32: 1 | G32: =VLOOKUP('Informasi Pokok'!D25,Parameter!E32:F36,2,0) | H32: 20 | I32: 0.2 | J32: 0.25 | K32: =H32*I32*J32 | L32: 25 | M32: 0.1 | N32: 0.4 | O32: =L32*M32*N32
D33: 2 | E33: PNS | F33: 2 | H33: 100 | I33: 0.2 | J33: 0.25 | K33: =H33*I33*J33 | L33: 50 | M33: 0.1 | N33: 0.4 | O33: =L33*M33*N33
D34: 3 | E34: Kontrak Swasta | F34: 3 | H34: 40 | I34: 0.2 | J34: 0.25 | K34: =H34*I34*J34 | L34: 75 | M34: 0.1 | N34: 0.4 | O34: =L34*M34*N34
D35: 4 | E35: Kontrak ASN/PPPK | F35: 4 | H35: 60 | I35: 0.2 | J35: 0.25 | K35: =H35*I35*J35 | L35: 100 | M35: 0.1 | N35: 0.4 | O35: =L35*M35*N35
D36: 5 | E36: Tetap Swasta | F36: 5 | H36: 80 | I36: 0.2 | J36: 0.25 | K36: =H36*I36*J36 | P36: =K33 | Q36: =K35 | R36: =K34 | S36: =K33 | U36: =VLOOKUP('Informasi Pokok'!$D$25,Parameter!E32:K36,7,0)
A37: (b) | B37: Bidang Usaha Pekerjaan
D38: 1 | E38: Perdagangan | H38: 20 | I38: 0.2 | J38: 0.3 | K38: =H38*I38*J38 | L38: 25 | M38: 0.1 | N38: 0.4 | O38: =L38*M38*N38
D39: 2 | E39: Jasa | H39: 40 | I39: 0.2 | J39: 0.3 | K39: =H39*I39*J39 | L39: 50 | M39: 0.1 | N39: 0.4 | O39: =L39*M39*N39
D40: 3 | E40: Pendidikan | H40: 60 | I40: 0.2 | J40: 0.3 | K40: =H40*I40*J40 | L40: 75 | M40: 0.1 | N40: 0.4 | O40: =L40*M40*N40
D41: 4 | E41: Kesehatan | H41: 80 | I41: 0.2 | J41: 0.3 | K41: =H41*I41*J41 | L41: 100 | M41: 0.1 | N41: 0.4 | O41: =L41*M41*N41
D42: 5 | E42: Pemerintahan | H42: 100 | I42: 0.2 | J42: 0.3 | K42: =H42*I42*J42
A43: (b) | B43: Bonafiditas Perusahaan
D44: 1 | E44: Bonafide | H44: 20 | I44: 0.2 | J44: 0.3 | K44: =H44*I44*J44 | L44: 25 | M44: 0.1 | N44: 0.4 | O44: =L44*M44*N44
D45: 2 | E45: Cukup Bonafide | H45: 40 | I45: 0.2 | J45: 0.3 | K45: =H45*I45*J45 | L45: 50 | M45: 0.1 | N45: 0.4 | O45: =L45*M45*N45
D46: 3 | E46: Kurang Bonafide | H46: 60 | I46: 0.2 | J46: 0.3 | K46: =H46*I46*J46 | L46: 75 | M46: 0.1 | N46: 0.4 | O46: =L46*M46*N46
D47: 4 | H47: 80 | I47: 0.2 | J47: 0.3 | K47: =H47*I47*J47 | L47: 100 | M47: 0.1 | N47: 0.4 | O47: =L47*M47*N47
D48: 5 | H48: 100 | I48: 0.2 | J48: 0.3 | K48: =H48*I48*J48
A49: (c) | B49: Reputasi
D50: 1 | E50: Tidak baik | H50: 0 | I50: 0.2 | J50: 0.3 | K50: =H50*I50*J50
D51: 2 | E51: Tidak dikenal | H51: 20 | I51: 0.2 | J51: 0.3 | K51: =H51*I51*J51
D52: 3 | E52: Dikenal namum kurang bersosialisasi | H52: 75 | I52: 0.2 | J52: 0.3 | K52: =H52*I52*J52
D53: 4 | E53: Dikenal baik | H53: 100 | I53: 0.2 | J53: 0.3 | K53: =H53*I53*J53 | P53: =K53 | Q53: =K52 | R53: =K51 | S53: =K50 | U53: =VLOOKUP('Informasi Pokok'!D34,Parameter!E50:K53,7,0)
A55: (a) | B55: Usia Pensiun
D56: 1 | E56: =IF($G$32<=2,Q254,R254) | H56: 20 | I56: 0.25 | J56: 0.25 | K56: =H56*I56*J56 | L56: 25 | M56: 0.3 | N56: 0.6 | O56: =L56*M56*N56 | T56: =IF(G32<=2,H253,H254)
D57: 2 | E57: =IF($G$32<=2,Q255,R255) | H57: 50 | I57: 0.25 | J57: 0.25 | K57: =H57*I57*J57 | L57: 50 | M57: 0.3 | N57: 0.6 | O57: =L57*M57*N57 | T57: =IF(G32<=2,I253,I254)
D58: 3 | E58: =IF($G$32<=2,Q256,R256) | H58: 75 | I58: 0.25 | J58: 0.25 | K58: =H58*I58*J58 | L58: 75 | M58: 0.3 | N58: 0.6 | O58: =L58*M58*N58
D59: 4 | E59: =IF($G$32<=2,Q257,R257) | H59: 100 | I59: 0.25 | J59: 0.24 | K59: =H59*I59*J59 | L59: 100 | M59: 0.3 | N59: 0.6 | O59: =L59*M59*N59 | P59: =K59 | Q59: =K58 | R59: =K57 | S59: =K56 | U59: =VLOOKUP($T$57,Parameter!E56:K59,7,0)
A61: (a) | B61: Surat Keterangan Bekerja
D62: 1 | E62: Tidak Ada | H62: 20 | I62: 0.1 | J62: 0.2 | K62: =H62*I62*J62 | L62: 25 | M62: 0.3 | N62: 0.6 | O62: =L62*M62*N62
D63: 2 | E63: Ada | H63: 100 | I63: 0.1 | J63: 0.3 | K63: =H63*I63*J63 | L63: 50 | M63: 0.3 | N63: 0.6 | O63: =L63*M63*N63 | P63: =K63 | Q63: =K62 | R63: =K61 | S63: 0 | U63: =VLOOKUP('Informasi Pokok'!$D$29,Parameter!E62:K63,7,0)
A65: (a) | B65: Slip Gaji
D66: 1 | E66: Tidak Ada | H66: 20 | I66: 0.1 | J66: 0.2 | K66: =H66*I66*J66 | L66: 25 | M66: 0.3 | N66: 0.6 | O66: =L66*M66*N66
D67: 2 | E67: Ada | H67: 100 | I67: 0.1 | J67: 0.3 | K67: =H67*I67*J67 | L67: 50 | M67: 0.3 | N67: 0.6 | O67: =L67*M67*N67 | P67: =K67 | Q67: =K66 | R67: =K65 | U67: =VLOOKUP('Informasi Pokok'!$D$30,Parameter!E66:K67,7,0)
L68: 75 | M68: 0.3 | N68: 0.6 | O68: =L68*M68*N68
L69: 100 | M69: 0.3 | N69: 0.6 | O69: =L69*M69*N69
A70: (a) | B70: Rekening Gaji
D71: 1 | E71: Tidak Ada | H71: 20 | I71: 0.1 | J71: 0.2 | K71: =H71*I71*J71 | L71: 25 | M71: 0.3 | N71: 0.6 | O71: =L71*M71*N71
D72: 2 | E72: Ada | H72: 100 | I72: 0.1 | J72: 0.3 | K72: =H72*I72*J72 | L72: 50 | M72: 0.3 | N72: 0.6 | O72: =L72*M72*N72 | P72: =K72 | Q72: =K71 | R72: =K70 | S72: =K69 | U72: =VLOOKUP('Informasi Pokok'!$D$31,Parameter!E71:K72,7,0)
L73: 75 | M73: 0.3 | N73: 0.6 | O73: =L73*M73*N73
A74: (a) | B74: System Angsuran
D75: 1 | E75: Tunai/Transfer | H75: 20 | I75: 0.1 | J75: 0.2 | K75: =H75*I75*J75 | L75: 25 | M75: 0.3 | N75: 0.6 | O75: =L75*M75*N75
D76: 2 | E76: Potong Gaji Langsung | H76: 100 | I76: 0.1 | J76: 0.3 | K76: =H76*I76*J76 | L76: 50 | M76: 0.3 | N76: 0.6 | O76: =L76*M76*N76
L77: 100 | M77: 0.3 | N77: 0.6 | O77: =L77*M77*N77
A80: STEP 4 - HUBUNGAN DENGAN PERBANKAN
A81: (a) | B81: Hubungan dengan perbankan (PG)
D82: 1 | E82: Belum Pernah | H82: 32 | I82: 0.25 | J82: 0.25 | K82: =H82*I82*J82 | L82: 0 | M82: 0.25 | N82: 0.4 | O82: =L82*M82*N82
D83: 2 | E83: Nasabah/debitur bank < 1 tahun | H83: 40 | I83: 0.25 | J83: 0.25 | K83: =H83*I83*J83 | L83: 40 | M83: 0.25 | N83: 0.4 | O83: =L83*M83*N83
D84: 3 | E84: Nasabah/debitur bank 1 - 3 tahun | H84: 80 | I84: 0.25 | J84: 0.25 | K84: =H84*I84*J84 | L84: 80 | M84: 0.25 | N84: 0.4 | O84: =L84*M84*N84
D85: 4 | E85: Nasabah/debitur bank > 3 tahun | H85: 100 | I85: 0.25 | J85: 0.25 | K85: =H85*I85*J85 | L85: 100 | M85: 0.25 | N85: 0.4 | O85: =L85*M85*N85 | P85: =K85 | Q85: =K84 | R85: =K83 | S85: =K82 | U85: =VLOOKUP('Informasi Pokok'!$D$48,Parameter!E82:K85,7,0)
A86: (d) | B86: Riwayat Kredit/Pemb di bank (SLIK) (PG)
D87: 1 | E87: Terdapat Kol 3,4 dan 5 di 12 bulan terakhir | H87: 0 | I87: 0.25 | J87: 0.28 | K87: =H87*I87*J87 | L87: 0 | M87: 0.25 | N87: 0.6 | O87: =L87*M87*N87
D88: 2 | E88: Terdapat Kol 2 di 12 bulan terakhir | H88: 25 | I88: 0.25 | J88: 0.28 | K88: =H88*I88*J88 | L88: 25 | M88: 0.25 | N88: 0.6 | O88: =L88*M88*N88
D89: 3 | E89: Belum memiliki kredit/Pembiayaan | H89: 75 | I89: 0.25 | J89: 0.28 | K89: =H89*I89*J89 | L89: 75 | M89: 0.25 | N89: 0.6 | O89: =L89*M89*N89
D90: 4 | E90: Tidak pernah terlambat 12 bulan terakhir | H90: 100 | I90: 0.25 | J90: 0.28 | K90: =H90*I90*J90 | L90: 100 | M90: 0.25 | N90: 0.6 | O90: =L90*M90*N90 | P90: =K90 | Q90: =K89 | R90: =K88 | S90: =K87 | U90: =VLOOKUP('Informasi Pokok'!$D$49,Parameter!E87:K90,7,0)
A92: (e) | B92: Pefindo | D92: 1 | E92: Risiko Sangat Tinggi | H92: 10 | I92: 0.25 | J92: 0.2 | K92: =H92*I92*J92
D93: 2 | E93: Risiko Tinggi | G93: <70 | H93: 25 | I93: 0.25 | J93: 0.2 | K93: =H93*I93*J93
D94: 3 | E94: Risiko Sedang | G94: >=70 sd <80 | H94: 50 | I94: 0.25 | J94: 0.2 | K94: =H94*I94*J94
D95: 4 | E95: Risiko Rendah | G95: >=80 sd <90 | H95: 75 | I95: 0.25 | J95: 0.2 | K95: =H95*I95*J95
D96: 5 | E96: Risiko Sangat Rendah | G96: >=90 | H96: 100 | I96: 0.25 | J96: 0.2 | K96: =H96*I96*J96 | Q96: =K95 | R96: =K94 | S96: =K93 | T96: =IF('Usulan Pembiayaan'!B71<70,"Risiko Tinggi",IF(AND('Usulan Pembiayaan'!B71>=70,'Usulan Pembiayaan'!B71<80),"Risiko Sedang",IF(AND('Usulan Pembiayaan'!B71>=80,'Usulan Pembiayaan'!B71<90),"Risiko Rendah",IF('Usulan Pembiayaan'!B71>=90,"Risiko Sangat Rendah")))) | V96: =VLOOKUP(T96,Parameter!E92:L96,7,0)
A98: RPC
D99: 1 | E99: ='Usulan Pembiayaan'!AB55 | H99: 0 | I99: 0.36 | J99: 0.5 | K99: =H99*I99*J99
D100: 2 | E100: ='Usulan Pembiayaan'!AC55 | H100: 50 | I100: 0.36 | J100: 0.5 | K100: =H100*I100*J100
D101: 3 | E101: ='Usulan Pembiayaan'!AD55 | H101: 75 | I101: 0.36 | J101: 0.5 | K101: =H101*I101*J101
D102: 4 | E102: ='Usulan Pembiayaan'!AE55 | H102: 100 | I102: 0.36 | J102: 0.5 | K102: =H102*I102*J102 | P102: =K102 | Q102: =K101 | R102: =K100 | S102: =K99 | U102: =MAX('Usulan Pembiayaan'!AF59:AF62)
A104: STEP 5 - JANGKA WAKTU
A105: (a) | B105: Jangka waktu
D106: 1 | E106: >8 Tahun | H106: 20 | I106: 0.1 | J106: 0.5 | K106: =H106*I106*J106 | L106: 25 | M106: 0.1 | N106: 1 | O106: =L106*M106*N106
D107: 2 | E107: 7 - 8 Tahun | H107: 40 | I107: 0.1 | J107: 0.5 | K107: =H107*I107*J107 | L107: 50 | M107: 0.1 | N107: 1 | O107: =L107*M107*N107 | Y107: =IF(N110<1,"Tidak ada",IF(N110<3,"Pasif atau kurang dari 3 kali perbulan",IF(AND(N110>=3,N110<=8),"Mutasi 3 - 8 kali perbulan",IF(N110>8,"Lebih dari 8 kali perbulan"))))
D108: 3 | E108: 5 - 6 Tahun | H108: 60 | I108: 0.1 | J108: 0.5 | K108: =H108*I108*J108 | L108: 75 | M108: 0.1 | N108: 1 | O108: =L108*M108*N108 | T108: ='Usulan Pembiayaan'!J54/12
D109: 4 | E109: 3 - 4 Tahun | H109: 80 | I109: 0.1 | J109: 0.5 | K109: =H109*I109*J109 | L109: 100 | M109: 0.1 | N109: 1 | O109: =L109*M109*N109
D110: 5 | E110: 1 - 2 Tahun | H110: 100 | I110: 0.1 | J110: 0.5 | K110: =H110*I110*J110 | P110: =K110 | Q110: =K108 | R110: =K107 | S110: =K106 | T110: =IF(T108<=0,"0",IF(T108<=2,"1 - 2 Tahun",IF(AND(T108>2,T108<=4),"3 - 4 Tahun",IF(AND(T108>4,T108<=6),"5 - 6 Tahun",IF(AND(T108>6,T108<=8),"7 - 8 Tahun",IF(T108>8,">8 Tahun")))))) | U110: =VLOOKUP(T110,E106:K110,7,0)
A112: (b) | B112: Pembiayaan ke- | D112: 1 | E112: 1-2 | H112: 50 | I112: 0.2 | J112: 0.2 | K112: =H112*I112*J112
...

Sheet Rating
B3: HIGH | C3: LOW | D3: RANK | E3: TINGKAT RATING | G3: RANK | H3: PD | I3: PENJELASAN DARI RATING
A4: 1 | B4: 100 | C4: 98 | D4: 1 | E4: AAA | F4: Outstanding | G4: 1 | H4: 0.0003 | I4: Ini adalah rating tertinggi dan terbaik yang diberikan kepada debitur. Kapasitas debitur untuk memenuhi komitmen keuangannya pada pinjaman bank dipandang tidak diragukan.
A5: 2 | B5: 97 | C5: 95 | D5: 2 | E5: AA+ | F5: Strong | G5: 2 | H5: 0.0003 | I5: Debitur yang diberikan rating ‘AA+’ hanya berbeda sedikit dari debitur yang diberikan rating tertinggi (AAA). Kapasitas debitur untuk memenuhi komitmen keuangannya pada pinjamannya sangat baik.
A6: 3 | B6: 94 | C6: 92 | D6: 3 | E6: AA | F6: Strong | G6: 3 | H6: 0.0003 | I6: Debitur yang diberikan rating ‘AA’ hanya berbeda sedikit dari debitur yang diberikan rating tertinggi (AAA). Kapasitas debitur untuk memenuhi komitmen keuangannya pada pinjamannya sangat baik.
A7: 4 | B7: 91 | C7: 89 | D7: 4 | E7: AA- | F7: Strong | G7: 4 | H7: 0.0003 | I7: Debitur yang diberikan rating ‘AA-’ hanya berbeda sedikit dari debitur yang diberikan rating tertinggi (AAA). Kapasitas debitur untuk memenuhi komitmen keuangannya pada pinjamannya sangat baik.
A8: 5 | B8: 88 | C8: 86 | D8: 5 | E8: A+ | F8: Good | G8: 5 | H8: 0.0006 | I8: Debitur yang diberikan rating ‘A+’ agak lebih rentan terhadap keadaan dan kondisi ekonomi yang memburuk dari pada debitur pada rating yang lebih tinggi. Meskipun demikian kapasitas debitur untuk memenuhi komitmen keuangannya pada obligasi masih kuat.
A9: 6 | B9: 85 | C9: 83 | D9: 6 | E9: A | F9: Good | G9: 6 | H9: 0.0004 | I9: Debitur yang diberikan rating ‘A’ agak lebih rentan terhadap keadaan dan kondisi ekonomi yang memburuk dari pada debitur pada rating yang lebih tinggi. Meskipun demikian kapasitas debitur untuk memenuhi komitmen keuangannya pada obligasi masih kuat.
A10: 7 | B10: 82 | C10: 80 | D10: 7 | E10: A- | F10: Good | G10: 7 | H10: 0.0005 | I10: Debitur yang diberikan rating ‘A-’ agak lebih rentan terhadap keadaan dan kondisi ekonomi yang memburuk dari pada debitur pada rating yang lebih tinggi. Meskipun demikian kapasitas debitur untuk memenuhi komitmen keuangannya pada obligasi masih kuat.
A11: 8 | B11: 79 | C11: 77 | D11: 8 | E11: BBB+ | F11: Average | G11: 8 | H11: 0.0018 | I11: Debitur yang mendapat rating ‘BBB+’ memperlihatkan kondisi yang memadai. Meskipun demikian kondisi ekonomi yang memburuk kemungkinan besar akan memperlemah kapasitas debitur untuk memenuhi komitmen keuangannya pada pinjamannya.
A12: 9 | B12: 76 | C12: 74 | D12: 9 | E12: BBB | F12: Average | G12: 9 | H12: 0.0029 | I12: Debitur yang mendapat rating ‘BBB’ memperlihatkan kondisi yang memadai. Meskipun demikian kondisi ekonomi yang memburuk kemungkinan besar akan memperlemah kapasitas debitur untuk memenuhi komitmen keuangannya pada pinjamannya.
A13: 10 | B13: 73 | C13: 71 | D13: 10 | E13: BBB- | F13: Average | G13: 10 | H13: 0.0033 | I13: Debitur yang mendapat rating ‘BBB-’ memperlihatkan kondisi yang memadai. Meskipun demikian kondisi ekonomi yang memburuk kemungkinan besar akan memperlemah kapasitas debitur untuk memenuhi komitmen keuangannya pada pinjamannya.
A14: 11 | B14: 70 | C14: 68 | D14: 11 | E14: BB+ | F14: Acceptable | G14: 11 | H14: 0.0048 | I14: Debitur yang diberikan rating ‘BB+’ lebih baik dibandingkan dengan debitur yang mendapat rating B dalam hal pembayaran pinjaman. Meskipun demikian, debitur ini menghadapi ketidakpastian yang besar pada kondisi bisnis, keuangan atau ekonomi yang memburuk yang dapat mengarah pada kapasitas debitur yang tidak memadai untuk memenuhi komitmen pinjamannya.
A15: 12 | B15: 67 | C15: 65 | D15: 12 | E15: BB | F15: Acceptable | G15: 12 | H15: 0.0107 | I15: Debitur yang diberikan rating ‘BB’ lebih baik dibandingkan dengan debitur yang mendapat rating B dalam hal pembayaran pinjaman. Meskipun demikian, debitur ini menghadapi ketidakpastian yang besar pada kondisi bisnis, keuangan atau ekonomi yang memburuk yang dapat mengarah pada kapasitas debitur yang tidak memadai untuk memenuhi komitmen pinjamannya.
... A23: 20 | B23: 43 | C23: 0 | D23: 20 | E23: D | F23: Doubtful | G23: 20 | H23: 1 | I23: Tidak prospektif. Rating ini diberikan kepada debitur yang diperkirakan akan menjadi kredit macet.
E24: Unrated | F24: Unrated | G24: 21
D26: 100 | E26: AAA | F26: 1
D27: 99 | E27: AAA | F27: 1
D28: 98 | E28: AAA | F28: 1
D29: 97 | E29: AA+ | F29: 2
D30: 96 | E30: AA+ | F30: 2
D31: 95 | E31: AA+ | F31: 2
D32: 94 | E32: AA | F32: 3
D33: 93 | E33: AA | F33: 3
D34: 92 | E34: AA | F34: 3
D35: 91 | E35: AA- | F35: 4
D36: 90 | E36: AA- | F36: 4
D37: 89 | E37: AA- | F37: 4
... D126: 0 | E126: D | F126: 20

Sheet SPPK
